Workbook

Sheet lc_detailed
B1: Asset Parameters (normalized by commodity feedstock) | R1: Duals | AO1: LCOE for assets with ethane capacity ($/t-ethylene) | AQ1: SEQ - CI | AR1: SEQ - CREDIT | AT1: NO SEQ - CI | AU1: NO SEQ - CREDIT | BE1: CHEM SEQUESTRATION - CARBON INTENSITY | BH1: CHEM SEQUESTRATION - CREDIT | BK1: NO CHEM SEQUESTRATION - CARBON INTENSITY | BN1: NO CHEM SEQUESTRATION - CREDIT | BR1: Carbon Content | BW1: Carbon Inputs | BZ1: Carbon Outputs | CH1: Assumptions
B2: id | C2: commodity | D2: CCS | E2: h2_consumption (MWh/t-CO2Captured) | F2: elec_consumption (MWh/t-CO2Captured) | G2: ethylene_production (t-ethylene/t-CO2Captured) | H2: natgas_production (MWh/t-CO2Captured) | I2: gasoline_production (MWh/t-CO2Captured) | J2: emission_rate (t-CO2/t-CO2Captured) | K2: investment_cost ($/yr per t-CO2Captured/hr) | L2: fixed_om_cost ($/yr per t-CO2Captured/hr) | M2: variable_om_cost WITHOUT LPG REVENUE ($/t-CO2Captured) | N2: variable_om_cost ($/t-CO2Captured) | O2: LPG_production (t-LPG/t-ethylene) | P2: LPG_production (t-LPG/t-CO2Captured) | R2: co2_sink ($/t) | S2: co2_captured ($/t) | T2: bioherb_supply ($/t) | U2: biowood_supply ($/t) | V2: bioagri_supply ($/t) | W2: LPG_demand ($/t-LPG) | X2: ethane_supply ($/MWh) | Y2: ethanol_balance ($/MWh) | Z2: ethanol_demand ($/MWh) | AA2: elec_demand ($/MWh) | AB2: h2_balance ($/MWh) | AC2: h2_demand ($/MWh) | AD2: gasoline_balance ($/MWh) | AE2: gasoline_demand ($/MWh) | AF2: diesel_balance ($/MWh) | AG2: diesel_demand ($/MWh) | AH2: jetfuel_balance ($/MWh) | AI2: jetfuel_demand ($/MWh) | AJ2: ng_balance ($/MWh) | AK2: ng_demand ($/MWh) | AL2: ethylene_balance ($/t) | AM2: ethylene_demand ($/t) | AO2: id_LC | AP2: commodity_LC | AQ2: LCOE ($/t-ethylene) | AR2: LCOE ($/t-ethylene) | AS2: Diff. Between Methods | AT2: LCOE ($/t-ethylene) | AU2: LCOE ($/t-ethylene) | AV2: Diff. Between Methods | AW2: h2_consumption | AX2: elec_consumption | AY2: co2captured_consumption | AZ2: natgas_production | BA2: gasoline_production | BB2: investment_cost | BC2: fixed_om_cost | BD2: variable_om_cost | BE2: CI | BF2: modified capture cost | BG2: modified emissions cost | BH2: CI | BI2: modified capture cost | BJ2: modified emissions cost | BK2: CI | BL2: modified capture cost | BM2: modified emissions cost | BN2: CI | BO2: modified capture cost | BP2: modified emissions cost | BR2: Ethylene (t-CO2/t-ethylene) | BS2: Gasoline (t-CO2/MWh-gasoline) | BT2: NG (t-CO2/MWh-NG) | BU2: LPG (t-CO2/t-LPG) | BW2: CO2Captured (t-CO2/t-CO2Captured) | BX2: CO2Captured - RECYCLE ADJUSTED (t-CO2/t-CO2Captured) | BZ2: Ethylene (t-CO2/t-CO2Captured) | CA2: NG (t-CO2/t-CO2Captured) | CB2: Emissions (t-CO2/t-CO2Captured) | CC2: LPG (t-CO2/t-CO2Captured) | CD2: Captured (t-CO2/t-CO2Captured) | CE2: Gasoline (t-CO2/t-CO2Captured) | CF2: RECYCLED Output (t-CO2/t-CO2Captured) | CH2: Ethylene Carbon Content | CI2: 3.14 | CJ2: t-CO2/t-ethylene
B3: Synthetic_Ethylene_Non_CCS | C3: CO2Captured | D3: 0 | E3: 5.4424707 | F3: 0.17633675 | G3: 0.11376564 | H3: 0.15787735 | I3: 0.76475308 | J3: 0.42937956 | K3: 174237.66 | L3: 95841.654 | M3: 2.9463017 | N3: =M3-(P3*W3) | O3: 1.01 | P3: =O3*G3 | R3: 122.13541 | W3: 420 | X3: 21.986353 | AO3: =B3 | AP3: =C3 | AQ3: =SUM(AW3:BD3)+BF3+BG3 | AR3: =SUM(AW3:BD3)+BI3+BJ3 | AS3: =AQ3-AR3 | AT3: =SUM(AW3:BD3)+BL3+BM3 | AU3: =SUM(AW3:BD3)+BO3+BP3 | AV3: =AT3-AU3 | AW3: =E3/G3*AB3 | AX3: =F3/G3*AA3 | AY3: =1/G3*(R3+S3) | AZ3: =H3/G3*AJ3*-1 | BA3: =I3/G3*AD3 | BB3: =K3/G3/(0.9*8760) | BC3: =L3/G3/(0.9*8760) | BD3: =N3 | BE3: =CF3-BX3-BZ3-CC3 | BF3: 0 | BG3: =BE3*R3 | BH3: =BX3-CF3-BZ3-CC3 | BI3: 0 | BJ3: =BH3*R3 | BK3: =BX3-CF3 | BL3: 0 | BM3: =BK3*R3 | BN3: =BX3-CF3 | BO3: 0 | BP3: =BN3*R3 | BR3: =$CI$2 | BS3: =$CI$3 | BT3: =$CI$4 | BU3: =$CI$5 | BW3: 1 | BX3: =BW3-CD3 | BZ3: =BR3*G3 | CA3: =BT3*H3 | CB3: =(BW3-BZ3-CA3-CE3-CC3)*(1-D3) | CC3: =BU3*O3 | CD3: =(BW3-BZ3-CA3-CE3-CC3)*(D3) | CE3: =BS3*I3 | CF3: =SUM(BZ3:CE3)-CD3 | CH3: Gasoline Carbon Content | CI3: 0.24123847 | CJ3: t-CO2/MWh-gasoline
B4: Synthetic_Ethylene_CCS_90 | C4: CO2Captured | D4: 0.9 | E4: 5.9243674 | F4: 0.24466847 | G4: 0.12383888 | H4: 0.1718564 | I4: 0.83246718 | J4: 0.37885469 | K4: 209498.32 | L4: 115165.85 | M4: 3.5425479 | N4: =M4-(P4*W4) | O4: 1.01 | P4: =O4*G4 | R4: 122.13541 | W4: 420 | X4: 21.986353 | AO4: =B4 | AP4: =C4 | AQ4: =SUM(AW4:BD4)+BF4+BG4 | AR4: =SUM(AW4:BD4)+BI4+BJ4 | AS4: =AQ4-AR4 | AT4: =SUM(AW4:BD4)+BL4+BM4 | AU4: =SUM(AW4:BD4)+BO4+BP4 | AV4: =AT4-AU4 | AW4: =E4/G4*AB4 | AX4: =F4/G4*AA4 | AY4: =1/G4*(R4+S4) | AZ4: =H4/G4*AJ4*-1 | BA4: =I4/G4*AD4 | BB4: =K4/G4/(0.9*8760) | BC4: =L4/G4/(0.9*8760) | BD4: =N4 | BE4: =CF4-BX4-BZ4-CC4 | BF4: 0 | BG4: =BE4*R4 | BH4: =BX4-CF4-BZ4-CC4 | BI4: 0 | BJ4: =BH4*R4 | BK4: =BX4-CF4 | BL4: 0 | BM4: =BK4*R4 | BN4: =BX4-CF4 | BO4: 0 | BP4: =BN4*R4 | BR4: =$CI$2 | BS4: =$CI$3 | BT4: =$CI$4 | BU4: =$CI$5 | BW4: 1 | BX4: =BW4-CD4 | BZ4: =BR4*G4 | CA4: =BT4*H4 | CB4: =(BW4-BZ4-CA4-CE4-CC4)*(1-D4) | CC4: =BU4*O4 | CD4: =(BW4-BZ4-CA4-CE4-CC4)*(D4) | CE4: =BS4*I4 | CF4: =SUM(BZ4:CE4)-CD4 | CH4: Natural Gas Carbon Content | CI4: 0.18104824 | CJ4: t-CO2/MWh-natgas
O5: 1.01 | W5: 420 | CH5: LPG Carbon Content | CI5: =0.22/14 | CJ5: t-CO2/t-LPG
O6: 1.01 | W6: 420 | CH6: Capacity Factor | CI6: 0.9 | CJ6: %
O7: 1.01 | W7: 420
O8: 1.01 | W8: 420
O9: 1.01 | W9: 420
O10: 1.01 | W10: 420
O11: 1.01 | W11: 420
O12: 1.01 | W12: 420
O13: 1.01 | W13: 420
O14: 1.01 | W14: 420
O15: 1.01 | W15: 420
O16: 1.01 | W16: 420
O17: 1.01 | W17: 420
O18: 1.01 | W18: 420
... O65: 1.01 | W65: 420

Sheet lc_summary_noseq
A1: Levelized cost for Synthetic Ethylene Production - $/GJ-ethylene - no chemicals CO2 sequestration | Q1: Assumptions
A2: id_LC | B2: h2_consumption | C2: elec_consumption | D2: co2captured_consumption | E2: natgas_production | F2: gasoline_production | G2: investment_cost | H2: fixed_om_cost | I2: variable_om_cost | J2: modified capture cost | K2: modified emissions cost | L2: CI | M2: LCOE ($/t-ethylene) | N2: LCOE ($/GJ-ethylene) | O2: CHECK LCOE ($/GJ-ethylene) | Q2: Ethylene LHV | R2: 45.6 | S2: GJ/t-ethylene
A3: =lc_detailed!AO3 | B3: =lc_detailed!AW3/$R$2 | C3: =lc_detailed!AX3/$R$2 | D3: =lc_detailed!AY3/$R$2 | E3: =lc_detailed!AZ3/$R$2 | F3: =lc_detailed!BA3/$R$2 | G3: =lc_detailed!BB3/$R$2 | H3: =lc_detailed!BC3/$R$2 | I3: =lc_detailed!BD3/$R$2 | J3: =lc_detailed!BL3/$R$2 | K3: =lc_detailed!BM3/$R$2 | L3: =lc_detailed!BK3 | M3: =lc_detailed!AT3 | N3: =M3/$R$2 | O3: =SUM(B3:K3)
A4: =lc_detailed!AO4 | B4: =lc_detailed!AW4/$R$2 | C4: =lc_detailed!AX4/$R$2 | D4: =lc_detailed!AY4/$R$2 | E4: =lc_detailed!AZ4/$R$2 | F4: =lc_detailed!BA4/$R$2 | G4: =lc_detailed!BB4/$R$2 | H4: =lc_detailed!BC4/$R$2 | I4: =lc_detailed!BD4/$R$2 | J4: =lc_detailed!BL4/$R$2 | K4: =lc_detailed!BM4/$R$2 | L4: =lc_detailed!BK4 | M4: =lc_detailed!AT4 | N4: =M4/$R$2 | O4: =SUM(B4:K4)

Sheet lc_summary_seq
A1: Levelized cost for Synthetic Ethylene Production - $/GJ-ethylene - chemicals CO2 sequestration | Q1: Assumptions
A2: id_LC | B2: h2_consumption | C2: elec_consumption | D2: co2captured_consumption | E2: natgas_production | F2: gasoline_production | G2: investment_cost | H2: fixed_om_cost | I2: variable_om_cost | J2: modified capture cost | K2: modified emissions cost | L2: CI | M2: LCOE ($/t-ethylene) | N2: LCOE ($/GJ-ethylene) | O2: CHECK LCOE ($/GJ-ethylene) | Q2: Ethylene LHV | R2: 45.6 | S2: GJ/t-ethylene
A3: =lc_detailed!AO3 | B3: =lc_detailed!AW3/$R$2 | C3: =lc_detailed!AX3/$R$2 | D3: =lc_detailed!AY3/$R$2 | E3: =lc_detailed!AZ3/$R$2 | F3: =lc_detailed!BA3/$R$2 | G3: =lc_detailed!BB3/$R$2 | H3: =lc_detailed!BC3/$R$2 | I3: =lc_detailed!BD3/$R$2 | J3: =lc_detailed!BF3/$R$2 | K3: =lc_detailed!BG3/$R$2 | L3: =lc_detailed!BH3 | M3: =lc_detailed!AQ3 | N3: =M3/$R$2 | O3: =SUM(B3:K3)
A4: =lc_detailed!AO4 | B4: =lc_detailed!AW4/$R$2 | C4: =lc_detailed!AX4/$R$2 | D4: =lc_detailed!AY4/$R$2 | E4: =lc_detailed!AZ4/$R$2 | F4: =lc_detailed!BA4/$R$2 | G4: =lc_detailed!BB4/$R$2 | H4: =lc_detailed!BC4/$R$2 | I4: =lc_detailed!BD4/$R$2 | J4: =lc_detailed!BF4/$R$2 | K4: =lc_detailed!BG4/$R$2 | L4: =lc_detailed!BH4 | M4: =lc_detailed!AQ4 | N4: =M4/$R$2 | O4: =SUM(B4:K4)
