Workbook

Sheet lc_detailed
B2: Asset Parameters (normalized by commodity feedstock) | P2: Duals | AL2: LCOE for ethanol production ($/MWh-ethanol) | AN2: CI | AO2: CREDIT | AP2: CI | AQ2: CREDIT | AZ2: NET CARBON INTENSITY + credit for capture | BC2: CREDIT for capture/storage + PAY for storage | BG2: Carbon Content | BK2: Carbon Inputs | BO2: Carbon Outputs | BT2: Sanity Checks
B3: id | C3: commodity | D3: elec_production (MWh/t-bio) | E3: elec_consumption (MWh/t-bio) | F3: ethanol_production (MWh-ethanol/t-bio) | G3: natgas_consumption (MWh/t-bio) | H3: co2_biomass_content (t-CO2/t-bio) | I3: capture_rate (t-CO2/t-bio) | J3: emission_rate (t-CO2/t-bio) | K3: calculated_emission_rate (t-CO2/t-bio) | L3: investment_cost ($/yr per t-bio/hr) | M3: fixed_om_cost ($/yr per t-bio/hr) | N3: variable_om_cost ($/t-bio) | P3: co2_sink ($/t) | Q3: co2_captured ($/t) | R3: biocorn_supply ($/t) | S3: bioherb_supply ($/t) | T3: biowood_supply ($/t) | U3: bioagri_supply ($/t) | V3: ethanol_balance ($/MWh) | W3: ethanol_demand ($/MWh) | X3: elec_demand ($/MWh) | Y3: h2_balance ($/MWh) | Z3: h2_demand ($/MWh) | AA3: gasoline_balance ($/MWh) | AB3: gasoline_demand ($/MWh) | AC3: diesel_balance ($/MWh) | AD3: diesel_demand ($/MWh) | AE3: jetfuel_balance ($/MWh) | AF3: jetfuel_demand ($/MWh) | AG3: ng_balance ($/MWh) | AH3: ng_demand ($/MWh) | AI3: ethylene_balance ($/t) | AJ3: ethylene_demand ($/t) | AL3: id_LC | AM3: commodity_LC | AN3: LCOE ($/MWh-ethanol) | AO3: LCOE ($/MWh-ethanol) | AP3: LCOE ($/GJ-ethanol) | AQ3: LCOE ($/GJ-ethanol) | AR3: Diff. Between Methods ($/MWh) | AS3: elec_production | AT3: elec_consumption | AU3: biomass_consumption | AV3: natgas_consumption | AW3: investment_cost | AX3: fixed_om_cost | AY3: variable_om_cost | AZ3: CI | BA3: modified capture cost | BB3: modified emissions cost | BC3: CI | BD3: modified capture cost | BE3: modified emissions cost | BG3: Biomass CO2 content (t-CO2/t-bio) | BH3: NG (t-CO2/MWh-NG) | BI3: Ethanol (t-CO2/MWh-ethanol) | BK3: Biomass (t-CO2/MWh-ethanol) | BL3: NG (t-CO2/MWh-ethanol) | BM3: Total input (t-CO2/MWh-ethanol) | BO3: Ethanol (t-CO2/MWh-ethanol) | BP3: Emissions (t-CO2/MWh-ethanol) | BQ3: Captured (t-CO2/MWh-ethanol) | BR3: Total Output (t-CO2/MWh-ethanol) | BT3: Carbon INPUT - OUTPUT
B4: SE_DryMill_Existing_Non_CCS | C4: Biomass_Corn | D4: 0 | E4: 0.06 | F4: 3.26 | G4: 0.75 | H4: 1.65 | I4: 0 | J4: =K4 -> 1.034529 | K4: =(BL4+(BK4-BO4-BQ4))*F4 -> 1.034529 | L4: 0 | M4: 154043.63 | N4: 79.65 | P4: 122.13541 | Q4: -10.071578 | S4: 73.297528 | T4: 77.15826 | U4: 59.694024 | X4: 26.556269 | Y4: 8.627892 | AA4: -96.133976 | AB4: -96.133976 | AG4: 4.754684 | AH4: -0.136283 | AI4: 576.81127 | AJ4: 576.81127 | AL4: =B4 -> SE_DryMill_Existing_Non_CCS | AM4: =C4 -> Biomass_Corn | AN4: =SUM(AS4:AY4)+BA4+BB4 -> 37.095845 | AO4: =SUM(AS4:AY4)+BD4+BE4 -> 37.095845 | AP4: =AN4/3.6 -> 10.304401 | AQ4: =AO4/3.6 -> 10.304401 | AR4: =AN4-AO4 -> 0 | AS4: =D4/F4*X4*-1 -> 0 | AT4: =E4/F4*X4 -> 0.48876569 | AU4: {=_xlfn.IFS(C4="Biomass_Corn", 1/F4*R4, C4="Biomass_Agri", 1/F4*U4, C4="Biomass_Wood", 1/F4*T4, C4="Biomass_Herb", 1/F4*S4)} -> 0 | AV4: =G4/F4*AG4 -> 1.093869 | AW4: =L4/F4/(0.9*8760) -> 0 | AX4: =M4/F4/(0.9*8760) -> 5.9934865 | AY4: =N4/F4 -> 24.432515 | AZ4: =SUM(BO4:BQ4)-BK4 -> 0.041652201 | BA4: =(P4+Q4)*-1*I4/F4 -> 0 | BB4: =AZ4*P4 -> 5.0872086 | BC4: =SUM(BO4:BP4)-BK4 -> 0.041652201 | BD4: =I4/F4*-1*Q4 -> 0 | BE4: =BC4*P4 -> 5.0872086 | BG4: =H4 -> 1.65 | BH4: 0.18104824 | BI4: 0.230447 | BK4: =BG4/F4 -> 0.50613497 | BL4: =BH4*G4/F4 -> 0.041652201 | BM4: =SUM(BK4:BL4) -> 0.54778717 | BO4: =BI4 -> 0.230447 | BP4: =J4/F4 -> 0.31734017 | BQ4: =I4/F4 -> 0 | BR4: =SUM(BO4:BQ4) -> 0.54778717 | BT4: =BM4-BR4 -> 0
B5: SE_Biochemical_Non_CCS | C5: Biomass_Herb | D5: 0.1227 | E5: 0 | F5: 1.5509 | G5: 0 | H5: 1.32 | I5: 0 | J5: =K5 -> 0.96259975 | K5: =(BL5+(BK5-BO5-BQ5))*F5 -> 0.96259975 | L5: 656536.27 | M5: 194987.35 | N5: 55.68 | P5: 122.13541 | Q5: -10.071578 | S5: 73.297528 | T5: 77.15826 | U5: 59.694024 | X5: 26.556269 | Y5: 8.627892 | AA5: -96.133976 | AB5: -96.133976 | AG5: 4.754684 | AH5: -0.136283 | AI5: 576.81127 | AJ5: 576.81127 | AL5: =B5 -> SE_Biochemical_Non_CCS | AM5: =C5 -> Biomass_Herb | AN5: =SUM(AS5:AY5)+BA5+BB5 -> 150.70322 | AO5: =SUM(AS5:AY5)+BD5+BE5 -> 150.70322 | AP5: =AN5/3.6 -> 41.862005 | AQ5: =AO5/3.6 -> 41.862005 | AR5: =AN5-AO5 -> 0 | AS5: =D5/F5*X5*-1 -> -2.1010086 | AT5: =E5/F5*X5 -> 0 | AU5: {=_xlfn.IFS(C5="Biomass_Corn", 1/F5*R5, C5="Biomass_Agri", 1/F5*U5, C5="Biomass_Wood", 1/F5*T5, C5="Biomass_Herb", 1/F5*S5)} -> 47.261286 | AV5: =G5/F5*AG5 -> 0 | AW5: =L5/F5/(0.9*8760) -> 53.694316 | AX5: =M5/F5/(0.9*8760) -> 15.946891 | AY5: =N5/F5 -> 35.901734 | AZ5: =SUM(BO5:BQ5)-BK5 -> 0 | BA5: =(P5+Q5)*-1*I5/F5 -> 0 | BB5: =AZ5*P5 -> 0 | BC5: =SUM(BO5:BP5)-BK5 -> 0 | BD5: =I5/F5*-1*Q5 -> 0 | BE5: =BC5*P5 -> 0 | BG5: =H5 -> 1.32 | BH5: 0.18104824 | BI5: 0.230447 | BK5: =BG5/F5 -> 0.85111871 | BL5: =BH5*G5/F5 -> 0 | BM5: =SUM(BK5:BL5) -> 0.85111871 | BO5: =BI5 -> 0.230447 | BP5: =J5/F5 -> 0.62067171 | BQ5: =I5/F5 -> 0 | BR5: =SUM(BO5:BQ5) -> 0.85111871 | BT5: =BM5-BR5 -> 0
B6: SE_Biochemical_CCS_20 | C6: Biomass_Herb | D6: 0.1227 | E6: 0 | F6: 1.5509 | G6: 0 | H6: 1.32 | I6: 0.19 | J6: =K6 -> 0.77259975 | K6: =(BL6+(BK6-BO6-BQ6))*F6 -> 0.77259975 | L6: 658128.84 | M6: 195838.97 | N6: 55.71 | P6: 122.13541 | Q6: -10.071578 | S6: 73.297528 | T6: 77.15826 | U6: 59.694024 | X6: 26.556269 | Y6: 8.627892 | AA6: -96.133976 | AB6: -96.133976 | AG6: 4.754684 | AH6: -0.136283 | AI6: 576.81127 | AJ6: 576.81127 | AL6: =B6 -> SE_Biochemical_CCS_20 | AM6: =C6 -> Biomass_Herb | AN6: =SUM(AS6:AY6)+BA6+BB6 -> 137.19357 | AO6: =SUM(AS6:AY6)+BD6+BE6 -> 137.19357 | AP6: =AN6/3.6 -> 38.109326 | AQ6: =AO6/3.6 -> 38.109326 | AR6: =AN6-AO6 -> 0 | AS6: =D6/F6*X6*-1 -> -2.1010086 | AT6: =E6/F6*X6 -> 0 | AU6: {=_xlfn.IFS(C6="Biomass_Corn", 1/F6*R6, C6="Biomass_Agri", 1/F6*U6, C6="Biomass_Wood", 1/F6*T6, C6="Biomass_Herb", 1/F6*S6)} -> 47.261286 | AV6: =G6/F6*AG6 -> 0 | AW6: =L6/F6/(0.9*8760) -> 53.824563 | AX6: =M6/F6/(0.9*8760) -> 16.01654 | AY6: =N6/F6 -> 35.921078 | AZ6: =SUM(BO6:BQ6)-BK6 -> 0 | BA6: =(P6+Q6)*-1*I6/F6 -> -13.728885 | BB6: =AZ6*P6 -> 0 | BC6: =SUM(BO6:BP6)-BK6 -> -0.12250951 | BD6: =I6/F6*-1*Q6 -> 1.2338641 | BE6: =BC6*P6 -> -14.962749 | BG6: =H6 -> 1.32 | BH6: 0.18104824 | BI6: 0.230447 | BK6: =BG6/F6 -> 0.85111871 | BL6: =BH6*G6/F6 -> 0 | BM6: =SUM(BK6:BL6) -> 0.85111871 | BO6: =BI6 -> 0.230447 | BP6: =J6/F6 -> 0.49816219 | BQ6: =I6/F6 -> 0.12250951 | BR6: =SUM(BO6:BQ6) -> 0.85111871 | BT6: =BM6-BR6 -> 0
B7: SE_Biochemical_CCS_86 | C7: Biomass_Agri | D7: 0.1227 | E7: 0.26 | F7: 1.5509 | G7: 0 | H7: 1.32 | I7: 0.83 | J7: =K7 -> 0.13259975 | K7: =(BL7+(BK7-BO7-BQ7))*F7 -> 0.13259975 | L7: 727064.6 | M7: 233553.61 | N7: 56.9 | P7: 122.13541 | Q7: -10.071578 | S7: 73.297528 | T7: 77.15826 | U7: 59.694024 | X7: 26.556269 | Y7: 8.627892 | AA7: -96.133976 | AB7: -96.133976 | AG7: 4.754684 | AH7: -0.136283 | AI7: 576.81127 | AJ7: 576.81127 | AL7: =B7 -> SE_Biochemical_CCS_86 | AM7: =C7 -> Biomass_Agri | AN7: =SUM(AS7:AY7)+BA7+BB7 -> 96.119179 | AO7: =SUM(AS7:AY7)+BD7+BE7 -> 96.119179 | AP7: =AN7/3.6 -> 26.699772 | AQ7: =AO7/3.6 -> 26.699772 | AR7: =AN7-AO7 -> 0 | AS7: =D7/F7*X7*-1 -> -2.1010086 | AT7: =E7/F7*X7 -> 4.4520149 | AU7: {=_xlfn.IFS(C7="Biomass_Corn", 1/F7*R7, C7="Biomass_Agri", 1/F7*U7, C7="Biomass_Wood", 1/F7*T7, C7="Biomass_Herb", 1/F7*S7)} -> 38.489925 | AV7: =G7/F7*AG7 -> 0 | AW7: =L7/F7/(0.9*8760) -> 59.462421 | AX7: =M7/F7/(0.9*8760) -> 19.101003 | AY7: =N7/F7 -> 36.688374 | AZ7: =SUM(BO7:BQ7)-BK7 -> 0 | BA7: =(P7+Q7)*-1*I7/F7 -> -59.973551 | BB7: =AZ7*P7 -> 0 | BC7: =SUM(BO7:BP7)-BK7 -> -0.53517313 | BD7: =I7/F7*-1*Q7 -> 5.3900379 | BE7: =BC7*P7 -> -65.363589 | BG7: =H7 -> 1.32 | BH7: 0.18104824 | BI7: 0.230447 | BK7: =BG7/F7 -> 0.85111871 | BL7: =BH7*G7/F7 -> 0 | BM7: =SUM(BK7:BL7) -> 0.85111871 | BO7: =BI7 -> 0.230447 | BP7: =J7/F7 -> 0.08549858 | BQ7: =I7/F7 -> 0.53517313 | BR7: =SUM(BO7:BQ7) -> 0.85111871 | BT7: =BM7-BR7 -> 0

Sheet lc_summary
B2: LC for bioethanol production $/GJ | R2: Conversion
B3: id_LC | C3: commodity_LC | D3: elec_production | E3: elec_consumption | F3: biomass_consumption | G3: natgas_consumption | H3: investment_cost | I3: fixed_om_cost | J3: variable_om_cost | K3: modified capture cost | L3: modified emissions cost | M3: CI | N3: LCOE ($/MWh-ethanol) | O3: LCOE ($/GJ-ethanol) | P3: CHECK LCOE ($/GJ-ethanol) | R3: Conversion | S3: 3.6 | T3: GJ/MWh
B4: =lc_detailed!AL4 -> SE_DryMill_Existing_Non_CCS | C4: =lc_detailed!AM4 -> Biomass_Corn | D4: =lc_detailed!AS4/$S$3 -> 0 | E4: =lc_detailed!AT4/$S$3 -> 0.13576825 | F4: =lc_detailed!AU4/$S$3 -> 0 | G4: =lc_detailed!AV4/$S$3 -> 0.30385251 | H4: =lc_detailed!AW4/$S$3 -> 0 | I4: =lc_detailed!AX4/$S$3 -> 1.6648573 | J4: =lc_detailed!AY4/$S$3 -> 6.7868098 | K4: =lc_detailed!BA4/$S$3 -> 0 | L4: =lc_detailed!BB4/$S$3 -> 1.4131135 | M4: =lc_detailed!AZ4 -> 0.041652201 | N4: =lc_detailed!AN4 -> 37.095845 | O4: =N4/$S$3 -> 10.304401 | P4: =SUM(D4:L4) -> 10.304401
B5: =lc_detailed!AL5 -> SE_Biochemical_Non_CCS | C5: =lc_detailed!AM5 -> Biomass_Herb | D5: =lc_detailed!AS5/$S$3 -> -0.58361349 | E5: =lc_detailed!AT5/$S$3 -> 0 | F5: =lc_detailed!AU5/$S$3 -> 13.128135 | G5: =lc_detailed!AV5/$S$3 -> 0 | H5: =lc_detailed!AW5/$S$3 -> 14.915088 | I5: =lc_detailed!AX5/$S$3 -> 4.4296919 | J5: =lc_detailed!AY5/$S$3 -> 9.972704 | K5: =lc_detailed!BA5/$S$3 -> 0 | L5: =lc_detailed!BB5/$S$3 -> 0 | M5: =lc_detailed!AZ5 -> 0 | N5: =lc_detailed!AN5 -> 150.70322 | O5: =N5/$S$3 -> 41.862005 | P5: =SUM(D5:L5) -> 41.862005
B6: =lc_detailed!AL6 -> SE_Biochemical_CCS_20 | C6: =lc_detailed!AM6 -> Biomass_Herb | D6: =lc_detailed!AS6/$S$3 -> -0.58361349 | E6: =lc_detailed!AT6/$S$3 -> 0 | F6: =lc_detailed!AU6/$S$3 -> 13.128135 | G6: =lc_detailed!AV6/$S$3 -> 0 | H6: =lc_detailed!AW6/$S$3 -> 14.951267 | I6: =lc_detailed!AX6/$S$3 -> 4.4490389 | J6: =lc_detailed!AY6/$S$3 -> 9.9780772 | K6: =lc_detailed!BA6/$S$3 -> -3.8135792 | L6: =lc_detailed!BB6/$S$3 -> 0 | M6: =lc_detailed!AZ6 -> 0 | N6: =lc_detailed!AN6 -> 137.19357 | O6: =N6/$S$3 -> 38.109326 | P6: =SUM(D6:L6) -> 38.109326
B7: =lc_detailed!AL7 -> SE_Biochemical_CCS_86 | C7: =lc_detailed!AM7 -> Biomass_Agri | D7: =lc_detailed!AS7/$S$3 -> -0.58361349 | E7: =lc_detailed!AT7/$S$3 -> 1.2366708 | F7: =lc_detailed!AU7/$S$3 -> 10.691646 | G7: =lc_detailed!AV7/$S$3 -> 0 | H7: =lc_detailed!AW7/$S$3 -> 16.517339 | I7: =lc_detailed!AX7/$S$3 -> 5.3058342 | J7: =lc_detailed!AY7/$S$3 -> 10.191215 | K7: =lc_detailed!BA7/$S$3 -> -16.65932 | L7: =lc_detailed!BB7/$S$3 -> 0 | M7: =lc_detailed!AZ7 -> 0 | N7: =lc_detailed!AN7 -> 96.119179 | O7: =N7/$S$3 -> 26.699772 | P7: =SUM(D7:L7) -> 26.699772
