Workbook

Sheet lc_detailed
B1: Asset Parameters (normalized by commodity feedstock) | Q1: Duals | AM1: LCOE for assets with ethane capacity ($/t-ethylene) | AO1: SEQ - CI | AP1: SEQ - CREDIT | AR1: NO SEQ - CI | AS1: NO SEQ - CREDIT | BD1: CHEM SEQUESTRATION - CARBON INTENSITY | BG1: CHEM SEQUESTRATION - CREDIT | BJ1: NO CHEM SEQUESTRATION - CARBON INTENSITY | BM1: NO CHEM SEQUESTRATION - CREDIT | BQ1: Carbon Content | BU1: Carbon Inputs | BY1: Carbon Outputs | CF1: Sanity Checks
B2: id | C2: commodity | D2: h2_consumption (MWh/MWh-ethane) | E2: h2_production (MWh/MWh-ethane) | F2: elec_consumption (MWh/MWh-ethane) | G2: ethylene_production (t-ethylene/MWh-ethane) | H2: natgas_consumption (MWh/MWh-ethane) | I2: natgas_production (MWh/MWh-ethane) | J2: capture_rate (t-CO2/MWh-ethane) | K2: emission_rate (t-CO2/MWh-ethane) | L2: investment_cost ($/yr per MW ethane) | M2: fixed_om_cost ($/yr per MW ethane) | N2: variable_om_cost ($/MWh-ethane) | O2: LPG_production (t-LPG/t-ethylene) | Q2: co2_sink ($/t) | R2: co2_captured ($/t) | S2: bioherb_supply ($/t) | T2: biowood_supply ($/t) | U2: bioagri_supply ($/t) | V2: ethane_supply ($/MWh) | W2: ethanol_balance ($/MWh) | X2: ethanol_demand ($/MWh) | Y2: elec_demand ($/MWh) | Z2: h2_balance ($/MWh) | AA2: h2_demand ($/MWh) | AB2: gasoline_balance ($/MWh) | AC2: gasoline_demand ($/MWh) | AD2: diesel_balance ($/MWh) | AE2: diesel_demand ($/MWh) | AF2: jetfuel_balance ($/MWh) | AG2: jetfuel_demand ($/MWh) | AH2: ng_balance ($/MWh) | AI2: ng_demand ($/MWh) | AJ2: ethylene_balance ($/t) | AK2: ethylene_demand ($/t) | AM2: id_LC | AN2: commodity_LC | AO2: LCOE ($/t-ethylene) | AP2: LCOE ($/t-ethylene) | AQ2: Diff. Between Methods | AR2: LCOE ($/t-ethylene) | AS2: LCOE ($/t-ethylene) | AT2: Diff. Between Methods | AU2: h2_consumption | AV2: h2_production | AW2: elec_consumption | AX2: ethane_consumption | AY2: natgas_consumption | AZ2: natgas_production | BA2: investment_cost | BB2: fixed_om_cost | BC2: variable_om_cost | BD2: CI | BE2: modified capture cost | BF2: modified emissions cost | BG2: CI | BH2: modified capture cost | BI2: modified emissions cost | BJ2: CI | BK2: modified capture cost | BL2: modified emissions cost | BM2: CI | BN2: modified capture cost | BO2: modified emissions cost | BQ2: Ethylene (t-CO2/t-ethylene) | BR2: Ethane (t-CO2/MWh-ethane) | BS2: NG (t-CO2/MWh-NG) | BU2: Ethane (t-CO2/t-ethylene) | BV2: NG (t-CO2/t-ethylene) | BW2: Total input (t-CO2/t-ethylene) | BY2: Ethylene (t-CO2/t-ethylene) | BZ2: NG (t-CO2/MWh-NG) | CA2: Emissions (t-CO2/t-ethylene) | CB2: Captured (t-CO2/t-ethylene) | CC2: LPG (t-CO2/t-ethylene) | CD2: Total Output (t-CO2/t-ethylene) | CF2: Diff. Between Input and Output CO2 (t-CO2/t-ethylene)
B3: CA_TSC | C3: Ethane | D3: 0 | E3: 0 | F3: 0 | G3: 0.053101897 | H3: 0.022701699 | I3: 0 | J3: 0 | K3: 0.02678347 | L3: 99124.32 | M3: 54251.998 | N3: 1.6761598 | O3: =CC3/0.22/14 -> 0.1980857 | Q3: 99.913298 | R3: -5.387721 | S3: 69.443859 | T3: 44.089523 | U3: 38.115627 | V3: 21.986353 | Y3: 19.219858 | Z3: 4.641256 | AH3: -3.135876 | AI3: -4.519557 | AJ3: 796.73601 | AK3: 0 | AM3: =B3 -> CA_TSC | AN3: =C3 -> Ethane | AO3: =SUM(AU3:BC3)+BE3+BF3 -> 861.01392 | AP3: =SUM(AU3:BC3)+BH3+BI3 -> 861.01392 | AQ3: =AO3-AP3 -> 0 | AR3: =SUM(AU3:BC3)+BK3+BL3 -> 1235.6992 | AS3: =SUM(AU3:BC3)+BN3+BO3 -> 1235.6992 | AT3: =AR3-AS3 -> 0 | AU3: =D3/G3*Z3 -> 0 | AV3: =E3/G3*Z3*-1 -> 0 | AW3: =F3/G3*Y3 -> 0 | AX3: =1/G3*V3 -> 414.04082 | AY3: =H3/G3*AH3 -> -1.3406246 | AZ3: =I3/G3*AH3*-1 -> 0 | BA3: =L3/G3/(0.9*8760) -> 236.76831 | BB3: =M3/G3/(0.9*8760) -> 129.5863 | BC3: =N3/G3 -> 31.564969 | BD3: =BZ3+CA3+CB3 -> 0.50437877 | BE3: =(Q3+R3)*-1*J3/G3 -> 0 | BF3: =BD3*Q3 -> 50.394146 | BG3: =BZ3+CA3 -> 0.50437877 | BH3: =R3*J3*-1/G3 -> 0 | BI3: =BG3*Q3 -> 50.394146 | BJ3: =SUM(BY3:CC3) -> 4.2544827 | BK3: =(Q3+R3)*-1*J3/G3 -> 0 | BL3: =BJ3*Q3 -> 425.0794 | BM3: =BY3+BZ3+CA3+CC3 -> 4.2544827 | BN3: =J3/G3*R3*-1 -> 0 | BO3: =Q3*BM3 -> 425.0794 | BQ3: 3.14 | BR3: 0.221811 | BS3: 0.18104824 | BU3: =1/G3*BR3 -> 4.1770824 | BV3: =H3/G3*BS3 -> 0.077400297 | BW3: =BU3+BV3 -> 4.2544827 | BY3: =BQ3 -> 3.14 | BZ3: =I3/G3*BS3 -> 0 | CA3: =K3/G3 -> 0.50437877 | CB3: =J3/G3 -> 0 | CC3: =BW3-SUM(BY3:CB3) -> 0.61010397 | CD3: =SUM(BY3:CC3) -> 4.2544827 | CF3: =CD3-BW3 -> 0
B4: SW_TSC | C4: Ethane | D4: 0 | E4: 0 | F4: 0 | G4: 0.053101897 | H4: 0.022701699 | I4: 0 | J4: 0 | K4: 0.02678347 | L4: 99124.32 | M4: 54251.998 | N4: 1.6761598 | O4: =CC4/0.22/14 -> 0.1980857 | Q4: 99.913298 | R4: -5.321206 | S4: 65.718464 | T4: 44.094475 | U4: 41.17053 | V4: 21.986353 | Y4: 20.088657 | Z4: 6.238322 | AH4: -1.277867 | AI4: -3.020989 | AJ4: 796.73601 | AK4: 0 | AM4: =B4 -> SW_TSC | AN4: =C4 -> Ethane | AO4: =SUM(AU4:BC4)+BE4+BF4 -> 861.80824 | AP4: =SUM(AU4:BC4)+BH4+BI4 -> 861.80824 | AQ4: =AO4-AP4 -> 0 | AR4: =SUM(AU4:BC4)+BK4+BL4 -> 1236.4935 | AS4: =SUM(AU4:BC4)+BN4+BO4 -> 1236.4935 | AT4: =AR4-AS4 -> 0 | AU4: =D4/G4*Z4 -> 0 | AV4: =E4/G4*Z4*-1 -> 0 | AW4: =F4/G4*Y4 -> 0 | AX4: =1/G4*V4 -> 414.04082 | AY4: =H4/G4*AH4 -> -0.54630349 | AZ4: =I4/G4*AH4*-1 -> 0 | BA4: =L4/G4/(0.9*8760) -> 236.76831 | BB4: =M4/G4/(0.9*8760) -> 129.5863 | BC4: =N4/G4 -> 31.564969 | BD4: =BZ4+CA4+CB4 -> 0.50437877 | BE4: =(Q4+R4)*-1*J4/G4 -> 0 | BF4: =BD4*Q4 -> 50.394146 | BG4: =BZ4+CA4 -> 0.50437877 | BH4: =R4*J4*-1/G4 -> 0 | BI4: =BG4*Q4 -> 50.394146 | BJ4: =SUM(BY4:CC4) -> 4.2544827 | BK4: =(Q4+R4)*-1*J4/G4 -> 0 | BL4: =BJ4*Q4 -> 425.0794 | BM4: =BY4+BZ4+CA4+CC4 -> 4.2544827 | BN4: =J4/G4*R4*-1 -> 0 | BO4: =Q4*BM4 -> 425.0794 | BQ4: 3.14 | BR4: 0.221811 | BS4: 0.18104824 | BU4: =1/G4*BR4 -> 4.1770824 | BV4: =H4/G4*BS4 -> 0.077400297 | BW4: =BU4+BV4 -> 4.2544827 | BY4: =BQ4 -> 3.14 | BZ4: =I4/G4*BS4 -> 0 | CA4: =K4/G4 -> 0.50437877 | CB4: =J4/G4 -> 0 | CC4: =BW4-SUM(BY4:CB4) -> 0.61010397 | CD4: =SUM(BY4:CC4) -> 4.2544827 | CF4: =CD4-BW4 -> 0
B5: NW_TSC | C5: Ethane | D5: 0 | E5: 0 | F5: 0 | G5: 0.053101897 | H5: 0.022701699 | I5: 0 | J5: 0 | K5: 0.02678347 | L5: 99124.32 | M5: 54251.998 | N5: 1.6761598 | O5: =CC5/0.22/14 -> 0.1980857 | Q5: 99.913298 | R5: -5.280129 | S5: 67.91568 | T5: 44.074162 | U5: 42.063157 | V5: 21.986353 | Y5: 19.074368 | Z5: 5.238745 | AH5: -2.438704 | AI5: -3.956322 | AJ5: 796.73601 | AK5: 0 | AM5: =B5 -> NW_TSC | AN5: =C5 -> Ethane | AO5: =SUM(AU5:BC5)+BE5+BF5 -> 861.31197 | AP5: =SUM(AU5:BC5)+BH5+BI5 -> 861.31197 | AQ5: =AO5-AP5 -> 0 | AR5: =SUM(AU5:BC5)+BK5+BL5 -> 1235.9972 | AS5: =SUM(AU5:BC5)+BN5+BO5 -> 1235.9972 | AT5: =AR5-AS5 -> 0 | AU5: =D5/G5*Z5 -> 0 | AV5: =E5/G5*Z5*-1 -> 0 | AW5: =F5/G5*Y5 -> 0 | AX5: =1/G5*V5 -> 414.04082 | AY5: =H5/G5*AH5 -> -1.0425752 | AZ5: =I5/G5*AH5*-1 -> 0 | BA5: =L5/G5/(0.9*8760) -> 236.76831 | BB5: =M5/G5/(0.9*8760) -> 129.5863 | BC5: =N5/G5 -> 31.564969 | BD5: =BZ5+CA5+CB5 -> 0.50437877 | BE5: =(Q5+R5)*-1*J5/G5 -> 0 | BF5: =BD5*Q5 -> 50.394146 | BG5: =BZ5+CA5 -> 0.50437877 | BH5: =R5*J5*-1/G5 -> 0 | BI5: =BG5*Q5 -> 50.394146 | BJ5: =SUM(BY5:CC5) -> 4.2544827 | BK5: =(Q5+R5)*-1*J5/G5 -> 0 | BL5: =BJ5*Q5 -> 425.0794 | BM5: =BY5+BZ5+CA5+CC5 -> 4.2544827 | BN5: =J5/G5*R5*-1 -> 0 | BO5: =Q5*BM5 -> 425.0794 | BQ5: 3.14 | BR5: 0.221811 | BS5: 0.18104824 | BU5: =1/G5*BR5 -> 4.1770824 | BV5: =H5/G5*BS5 -> 0.077400297 | BW5: =BU5+BV5 -> 4.2544827 | BY5: =BQ5 -> 3.14 | BZ5: =I5/G5*BS5 -> 0 | CA5: =K5/G5 -> 0.50437877 | CB5: =J5/G5 -> 0 | CC5: =BW5-SUM(BY5:CB5) -> 0.61010397 | CD5: =SUM(BY5:CC5) -> 4.2544827 | CF5: =CD5-BW5 -> 0
B6: TX_TSC | C6: Ethane | D6: 0 | E6: 0 | F6: 0 | G6: 0.053101897 | H6: 0.022701699 | I6: 0 | J6: 0 | K6: 0.02678347 | L6: 99124.32 | M6: 54251.998 | N6: 1.6761598 | O6: =CC6/0.22/14 -> 0.1980857 | Q6: 99.913298 | R6: -4.998843 | S6: 65.086749 | T6: 44.879451 | U6: 38.220582 | V6: 21.986353 | Y6: 20.95841 | Z6: 6.059849 | AH6: -1.481188 | AI6: -3.21388 | AJ6: 796.73601 | AK6: 796.73601 | AM6: =B6 -> TX_TSC | AN6: =C6 -> Ethane | AO6: =SUM(AU6:BC6)+BE6+BF6 -> 861.72132 | AP6: =SUM(AU6:BC6)+BH6+BI6 -> 861.72132 | AQ6: =AO6-AP6 -> 0 | AR6: =SUM(AU6:BC6)+BK6+BL6 -> 1236.4066 | AS6: =SUM(AU6:BC6)+BN6+BO6 -> 1236.4066 | AT6: =AR6-AS6 -> 0 | AU6: =D6/G6*Z6 -> 0 | AV6: =E6/G6*Z6*-1 -> 0 | AW6: =F6/G6*Y6 -> 0 | AX6: =1/G6*V6 -> 414.04082 | AY6: =H6/G6*AH6 -> -0.63322566 | AZ6: =I6/G6*AH6*-1 -> 0 | BA6: =L6/G6/(0.9*8760) -> 236.76831 | BB6: =M6/G6/(0.9*8760) -> 129.5863 | BC6: =N6/G6 -> 31.564969 | BD6: =BZ6+CA6+CB6 -> 0.50437877 | BE6: =(Q6+R6)*-1*J6/G6 -> 0 | BF6: =BD6*Q6 -> 50.394146 | BG6: =BZ6+CA6 -> 0.50437877 | BH6: =R6*J6*-1/G6 -> 0 | BI6: =BG6*Q6 -> 50.394146 | BJ6: =SUM(BY6:CC6) -> 4.2544827 | BK6: =(Q6+R6)*-1*J6/G6 -> 0 | BL6: =BJ6*Q6 -> 425.0794 | BM6: =BY6+BZ6+CA6+CC6 -> 4.2544827 | BN6: =J6/G6*R6*-1 -> 0 | BO6: =Q6*BM6 -> 425.0794 | BQ6: 3.14 | BR6: 0.221811 | BS6: 0.18104824 | BU6: =1/G6*BR6 -> 4.1770824 | BV6: =H6/G6*BS6 -> 0.077400297 | BW6: =BU6+BV6 -> 4.2544827 | BY6: =BQ6 -> 3.14 | BZ6: =I6/G6*BS6 -> 0 | CA6: =K6/G6 -> 0.50437877 | CB6: =J6/G6 -> 0 | CC6: =BW6-SUM(BY6:CB6) -> 0.61010397 | CD6: =SUM(BY6:CC6) -> 4.2544827 | CF6: =CD6-BW6 -> 0
B7: NCEN_TSC | C7: Ethane | D7: 0 | E7: 0 | F7: 0 | G7: 0.053101897 | H7: 0.022701699 | I7: 0 | J7: 0 | K7: 0.02678347 | L7: 99124.32 | M7: 54251.998 | N7: 1.6761598 | O7: =CC7/0.22/14 -> 0.1980857 | Q7: 99.913298 | R7: -6.08881 | S7: 66.120495 | T7: 43.630616 | U7: 43.105329 | V7: 21.986353 | Y7: 22.136932 | Z7: 6.801534 | AH7: -0.824778 | AI7: -3.075704 | AJ7: 796.73601 | AK7: 796.73601 | AM7: =B7 -> NCEN_TSC | AN7: =C7 -> Ethane | AO7: =SUM(AU7:BC7)+BE7+BF7 -> 862.00194 | AP7: =SUM(AU7:BC7)+BH7+BI7 -> 862.00194 | AQ7: =AO7-AP7 -> 0 | AR7: =SUM(AU7:BC7)+BK7+BL7 -> 1236.6872 | AS7: =SUM(AU7:BC7)+BN7+BO7 -> 1236.6872 | AT7: =AR7-AS7 -> 0 | AU7: =D7/G7*Z7 -> 0 | AV7: =E7/G7*Z7*-1 -> 0 | AW7: =F7/G7*Y7 -> 0 | AX7: =1/G7*V7 -> 414.04082 | AY7: =H7/G7*AH7 -> -0.3526025 | AZ7: =I7/G7*AH7*-1 -> 0 | BA7: =L7/G7/(0.9*8760) -> 236.76831 | BB7: =M7/G7/(0.9*8760) -> 129.5863 | BC7: =N7/G7 -> 31.564969 | BD7: =BZ7+CA7+CB7 -> 0.50437877 | BE7: =(Q7+R7)*-1*J7/G7 -> 0 | BF7: =BD7*Q7 -> 50.394146 | BG7: =BZ7+CA7 -> 0.50437877 | BH7: =R7*J7*-1/G7 -> 0 | BI7: =BG7*Q7 -> 50.394146 | BJ7: =SUM(BY7:CC7) -> 4.2544827 | BK7: =(Q7+R7)*-1*J7/G7 -> 0 | BL7: =BJ7*Q7 -> 425.0794 | BM7: =BY7+BZ7+CA7+CC7 -> 4.2544827 | BN7: =J7/G7*R7*-1 -> 0 | BO7: =Q7*BM7 -> 425.0794 | BQ7: 3.14 | BR7: 0.221811 | BS7: 0.18104824 | BU7: =1/G7*BR7 -> 4.1770824 | BV7: =H7/G7*BS7 -> 0.077400297 | BW7: =BU7+BV7 -> 4.2544827 | BY7: =BQ7 -> 3.14 | BZ7: =I7/G7*BS7 -> 0 | CA7: =K7/G7 -> 0.50437877 | CB7: =J7/G7 -> 0 | CC7: =BW7-SUM(BY7:CB7) -> 0.61010397 | CD7: =SUM(BY7:CC7) -> 4.2544827 | CF7: =CD7-BW7 -> 0
B8: CEN_TSC | C8: Ethane | D8: 0 | E8: 0 | F8: 0 | G8: 0.053101897 | H8: 0.022701699 | I8: 0 | J8: 0 | K8: 0.02678347 | L8: 99124.32 | M8: 54251.998 | N8: 1.6761598 | O8: =CC8/0.22/14 -> 0.1980857 | Q8: 99.913298 | R8: -6.197641 | S8: 65.135812 | T8: 43.37233 | U8: 42.438418 | V8: 21.986353 | Y8: 21.530919 | Z8: 6.288532 | AH8: -1.431457 | AI8: -3.351826 | AJ8: 796.73601 | AK8: 796.73601 | AM8: =B8 -> CEN_TSC | AN8: =C8 -> Ethane | AO8: =SUM(AU8:BC8)+BE8+BF8 -> 861.74258 | AP8: =SUM(AU8:BC8)+BH8+BI8 -> 861.74258 | AQ8: =AO8-AP8 -> 0 | AR8: =SUM(AU8:BC8)+BK8+BL8 -> 1236.4278 | AS8: =SUM(AU8:BC8)+BN8+BO8 -> 1236.4278 | AT8: =AR8-AS8 -> 0 | AU8: =D8/G8*Z8 -> 0 | AV8: =E8/G8*Z8*-1 -> 0 | AW8: =F8/G8*Y8 -> 0 | AX8: =1/G8*V8 -> 414.04082 | AY8: =H8/G8*AH8 -> -0.61196506 | AZ8: =I8/G8*AH8*-1 -> 0 | BA8: =L8/G8/(0.9*8760) -> 236.76831 | BB8: =M8/G8/(0.9*8760) -> 129.5863 | BC8: =N8/G8 -> 31.564969 | BD8: =BZ8+CA8+CB8 -> 0.50437877 | BE8: =(Q8+R8)*-1*J8/G8 -> 0 | BF8: =BD8*Q8 -> 50.394146 | BG8: =BZ8+CA8 -> 0.50437877 | BH8: =R8*J8*-1/G8 -> 0 | BI8: =BG8*Q8 -> 50.394146 | BJ8: =SUM(BY8:CC8) -> 4.2544827 | BK8: =(Q8+R8)*-1*J8/G8 -> 0 | BL8: =BJ8*Q8 -> 425.0794 | BM8: =BY8+BZ8+CA8+CC8 -> 4.2544827 | BN8: =J8/G8*R8*-1 -> 0 | BO8: =Q8*BM8 -> 425.0794 | BQ8: 3.14 | BR8: 0.221811 | BS8: 0.18104824 | BU8: =1/G8*BR8 -> 4.1770824 | BV8: =H8/G8*BS8 -> 0.077400297 | BW8: =BU8+BV8 -> 4.2544827 | BY8: =BQ8 -> 3.14 | BZ8: =I8/G8*BS8 -> 0 | CA8: =K8/G8 -> 0.50437877 | CB8: =J8/G8 -> 0 | CC8: =BW8-SUM(BY8:CB8) -> 0.61010397 | CD8: =SUM(BY8:CC8) -> 4.2544827 | CF8: =CD8-BW8 -> 0
B9: SE_TSC | C9: Ethane | D9: 0 | E9: 0 | F9: 0 | G9: 0.053101897 | H9: 0.022701699 | I9: 0 | J9: 0 | K9: 0.02678347 | L9: 99124.32 | M9: 54251.998 | N9: 1.6761598 | O9: =CC9/0.22/14 -> 0.1980857 | Q9: 99.913298 | R9: -6.084348 | S9: 64.970397 | T9: 43.861592 | U9: 39.255601 | V9: 21.986353 | Y9: 21.109138 | Z9: 6.240639 | AH9: -1.452344 | AI9: -3.071509 | AJ9: 796.73601 | AK9: 796.73601 | AM9: =B9 -> SE_TSC | AN9: =C9 -> Ethane | AO9: =SUM(AU9:BC9)+BE9+BF9 -> 861.73365 | AP9: =SUM(AU9:BC9)+BH9+BI9 -> 861.73365 | AQ9: =AO9-AP9 -> 0 | AR9: =SUM(AU9:BC9)+BK9+BL9 -> 1236.4189 | AS9: =SUM(AU9:BC9)+BN9+BO9 -> 1236.4189 | AT9: =AR9-AS9 -> 0 | AU9: =D9/G9*Z9 -> 0 | AV9: =E9/G9*Z9*-1 -> 0 | AW9: =F9/G9*Y9 -> 0 | AX9: =1/G9*V9 -> 414.04082 | AY9: =H9/G9*AH9 -> -0.6208945 | AZ9: =I9/G9*AH9*-1 -> 0 | BA9: =L9/G9/(0.9*8760) -> 236.76831 | BB9: =M9/G9/(0.9*8760) -> 129.5863 | BC9: =N9/G9 -> 31.564969 | BD9: =BZ9+CA9+CB9 -> 0.50437877 | BE9: =(Q9+R9)*-1*J9/G9 -> 0 | BF9: =BD9*Q9 -> 50.394146 | BG9: =BZ9+CA9 -> 0.50437877 | BH9: =R9*J9*-1/G9 -> 0 | BI9: =BG9*Q9 -> 50.394146 | BJ9: =SUM(BY9:CC9) -> 4.2544827 | BK9: =(Q9+R9)*-1*J9/G9 -> 0 | BL9: =BJ9*Q9 -> 425.0794 | BM9: =BY9+BZ9+CA9+CC9 -> 4.2544827 | BN9: =J9/G9*R9*-1 -> 0 | BO9: =Q9*BM9 -> 425.0794 | BQ9: 3.14 | BR9: 0.221811 | BS9: 0.18104824 | BU9: =1/G9*BR9 -> 4.1770824 | BV9: =H9/G9*BS9 -> 0.077400297 | BW9: =BU9+BV9 -> 4.2544827 | BY9: =BQ9 -> 3.14 | BZ9: =I9/G9*BS9 -> 0 | CA9: =K9/G9 -> 0.50437877 | CB9: =J9/G9 -> 0 | CC9: =BW9-SUM(BY9:CB9) -> 0.61010397 | CD9: =SUM(BY9:CC9) -> 4.2544827 | CF9: =CD9-BW9 -> 0
B10: MIDAT_TSC | C10: Ethane | D10: 0 | E10: 0 | F10: 0 | G10: 0.053101897 | H10: 0.022701699 | I10: 0 | J10: 0 | K10: 0.02678347 | L10: 99124.32 | M10: 54251.998 | N10: 1.6761598 | O10: =CC10/0.22/14 -> 0.1980857 | Q10: 99.913298 | R10: -15.650257 | S10: 63.953341 | T10: 39.720462 | U10: 40.53758 | V10: 21.986353 | Y10: 21.699949 | Z10: 8.045609 | AH10: -0.930222 | AI10: -2.781275 | AJ10: 796.73601 | AK10: 796.73601 | AM10: =B10 -> MIDAT_TSC | AN10: =C10 -> Ethane | AO10: =SUM(AU10:BC10)+BE10+BF10 -> 861.95686 | AP10: =SUM(AU10:BC10)+BH10+BI10 -> 861.95686 | AQ10: =AO10-AP10 -> 0 | AR10: =SUM(AU10:BC10)+BK10+BL10 -> 1236.6421 | AS10: =SUM(AU10:BC10)+BN10+BO10 -> 1236.6421 | AT10: =AR10-AS10 -> 0 | AU10: =D10/G10*Z10 -> 0 | AV10: =E10/G10*Z10*-1 -> 0 | AW10: =F10/G10*Y10 -> 0 | AX10: =1/G10*V10 -> 414.04082 | AY10: =H10/G10*AH10 -> -0.39768108 | AZ10: =I10/G10*AH10*-1 -> 0 | BA10: =L10/G10/(0.9*8760) -> 236.76831 | BB10: =M10/G10/(0.9*8760) -> 129.5863 | BC10: =N10/G10 -> 31.564969 | BD10: =BZ10+CA10+CB10 -> 0.50437877 | BE10: =(Q10+R10)*-1*J10/G10 -> 0 | BF10: =BD10*Q10 -> 50.394146 | BG10: =BZ10+CA10 -> 0.50437877 | BH10: =R10*J10*-1/G10 -> 0 | BI10: =BG10*Q10 -> 50.394146 | BJ10: =SUM(BY10:CC10) -> 4.2544827 | BK10: =(Q10+R10)*-1*J10/G10 -> 0 | BL10: =BJ10*Q10 -> 425.0794 | BM10: =BY10+BZ10+CA10+CC10 -> 4.2544827 | BN10: =J10/G10*R10*-1 -> 0 | BO10: =Q10*BM10 -> 425.0794 | BQ10: 3.14 | BR10: 0.221811 | BS10: 0.18104824 | BU10: =1/G10*BR10 -> 4.1770824 | BV10: =H10/G10*BS10 -> 0.077400297 | BW10: =BU10+BV10 -> 4.2544827 | BY10: =BQ10 -> 3.14 | BZ10: =I10/G10*BS10 -> 0 | CA10: =K10/G10 -> 0.50437877 | CB10: =J10/G10 -> 0 | CC10: =BW10-SUM(BY10:CB10) -> 0.61010397 | CD10: =SUM(BY10:CC10) -> 4.2544827 | CF10: =CD10-BW10 -> 0
B11: NE_TSC | C11: Ethane | D11: 0 | E11: 0 | F11: 0 | G11: 0.053101897 | H11: 0.022701699 | I11: 0 | J11: 0 | K11: 0.02678347 | L11: 99124.32 | M11: 54251.998 | N11: 1.6761598 | O11: =CC11/0.22/14 -> 0.1980857 | Q11: 99.913298 | R11: -21.727401 | S11: 66.936657 | T11: 41.693039 | U11: 41.333943 | V11: 21.986353 | Y11: 20.978032 | Z11: 12.546751 | AH11: 5.888729 | AI11: 0 | AJ11: 796.73601 | AK11: 0 | AM11: =B11 -> NE_TSC | AN11: =C11 -> Ethane | AO11: =SUM(AU11:BC11)+BE11+BF11 -> 864.87205 | AP11: =SUM(AU11:BC11)+BH11+BI11 -> 864.87205 | AQ11: =AO11-AP11 -> 0 | AR11: =SUM(AU11:BC11)+BK11+BL11 -> 1239.5573 | AS11: =SUM(AU11:BC11)+BN11+BO11 -> 1239.5573 | AT11: =AR11-AS11 -> 0 | AU11: =D11/G11*Z11 -> 0 | AV11: =E11/G11*Z11*-1 -> 0 | AW11: =F11/G11*Y11 -> 0 | AX11: =1/G11*V11 -> 414.04082 | AY11: =H11/G11*AH11 -> 2.5175024 | AZ11: =I11/G11*AH11*-1 -> 0 | BA11: =L11/G11/(0.9*8760) -> 236.76831 | BB11: =M11/G11/(0.9*8760) -> 129.5863 | BC11: =N11/G11 -> 31.564969 | BD11: =BZ11+CA11+CB11 -> 0.50437877 | BE11: =(Q11+R11)*-1*J11/G11 -> 0 | BF11: =BD11*Q11 -> 50.394146 | BG11: =BZ11+CA11 -> 0.50437877 | BH11: =R11*J11*-1/G11 -> 0 | BI11: =BG11*Q11 -> 50.394146 | BJ11: =SUM(BY11:CC11) -> 4.2544827 | BK11: =(Q11+R11)*-1*J11/G11 -> 0 | BL11: =BJ11*Q11 -> 425.0794 | BM11: =BY11+BZ11+CA11+CC11 -> 4.2544827 | BN11: =J11/G11*R11*-1 -> 0 | BO11: =Q11*BM11 -> 425.0794 | BQ11: 3.14 | BR11: 0.221811 | BS11: 0.18104824 | BU11: =1/G11*BR11 -> 4.1770824 | BV11: =H11/G11*BS11 -> 0.077400297 | BW11: =BU11+BV11 -> 4.2544827 | BY11: =BQ11 -> 3.14 | BZ11: =I11/G11*BS11 -> 0 | CA11: =K11/G11 -> 0.50437877 | CB11: =J11/G11 -> 0 | CC11: =BW11-SUM(BY11:CB11) -> 0.61010397 | CD11: =SUM(BY11:CC11) -> 4.2544827 | CF11: =CD11-BW11 -> 0
B12: CA_TSC+CC90 | C12: Ethane | D12: 0 | E12: 0 | F12: 0.0080529664 | G12: 0.053101897 | H12: 0.022701699 | I12: 0 | J12: 0.024105123 | K12: 0.002678347 | L12: 106875.17 | M12: 58496.387 | N12: 1.8072241 | O12: =CC12/0.22/14 -> 0.1980857 | Q12: 99.913298 | R12: -5.387721 | S12: 69.443859 | T12: 44.089523 | U12: 38.115627 | V12: 21.986353 | Y12: 19.219858 | Z12: 4.641256 | AH12: -3.135876 | AI12: -4.519557 | AJ12: 796.73601 | AK12: 0 | AM12: =B12 -> CA_TSC+CC90 | AN12: =C12 -> Ethane | AO12: =SUM(AU12:BC12)+BE12+BF12 -> 852.1396 | AP12: =SUM(AU12:BC12)+BH12+BI12 -> 852.1396 | AQ12: =AO12-AP12 -> 0 | AR12: =SUM(AU12:BC12)+BK12+BL12 -> 1226.8249 | AS12: =SUM(AU12:BC12)+BN12+BO12 -> 1226.8249 | AT12: =AR12-AS12 -> 0 | AU12: =D12/G12*Z12 -> 0 | AV12: =E12/G12*Z12*-1 -> 0 | AW12: =F12/G12*Y12 -> 2.9147145 | AX12: =1/G12*V12 -> 414.04082 | AY12: =H12/G12*AH12 -> -1.3406246 | AZ12: =I12/G12*AH12*-1 -> 0 | BA12: =L12/G12/(0.9*8760) -> 255.28198 | BB12: =M12/G12/(0.9*8760) -> 139.72444 | BC12: =N12/G12 -> 34.033136 | BD12: =BZ12+CA12+CB12 -> 0.50437877 | BE12: =(Q12+R12)*-1*J12/G12 -> -42.909025 | BF12: =BD12*Q12 -> 50.394146 | BG12: =BZ12+CA12 -> 0.050437877 | BH12: =R12*J12*-1/G12 -> 2.4457069 | BI12: =BG12*Q12 -> 5.0394146 | BJ12: =SUM(BY12:CC12) -> 4.2544827 | BK12: =(Q12+R12)*-1*J12/G12 -> -42.909025 | BL12: =BJ12*Q12 -> 425.0794 | BM12: =BY12+BZ12+CA12+CC12 -> 3.8005418 | BN12: =J12/G12*R12*-1 -> 2.4457069 | BO12: =Q12*BM12 -> 379.72467 | BQ12: 3.14 | BR12: 0.221811 | BS12: 0.18104824 | BU12: =1/G12*BR12 -> 4.1770824 | BV12: =H12/G12*BS12 -> 0.077400297 | BW12: =BU12+BV12 -> 4.2544827 | BY12: =BQ12 -> 3.14 | BZ12: =I12/G12*BS12 -> 0 | CA12: =K12/G12 -> 0.050437877 | CB12: =J12/G12 -> 0.45394089 | CC12: =BW12-SUM(BY12:CB12) -> 0.61010397 | CD12: =SUM(BY12:CC12) -> 4.2544827 | CF12: =CD12-BW12 -> 0
B13: CA_TSC:H2 | C13: Ethane | D13: 0 | E13: 0.15985314 | F13: 0 | G13: 0.053101897 | H13: 0.13183229 | I13: 0 | J13: 0 | K13: 0.04654137 | L13: 99124.32 | M13: 54251.998 | N13: 1.6761598 | O13: =CC13/0.22/14 -> 0.1980857 | Q13: 99.913298 | R13: -5.387721 | S13: 69.443859 | T13: 44.089523 | U13: 38.115627 | V13: 21.986353 | Y13: 19.219858 | Z13: 4.641256 | AH13: -3.135876 | AI13: -4.519557 | AJ13: 796.73601 | AK13: 0 | AM13: =B13 -> CA_TSC:H2 | AN13: =C13 -> Ethane | AO13: =SUM(AU13:BC13)+BE13+BF13 -> 877.77298 | AP13: =SUM(AU13:BC13)+BH13+BI13 -> 877.77298 | AQ13: =AO13-AP13 -> 0 | AR13: =SUM(AU13:BC13)+BK13+BL13 -> 1252.4582 | AS13: =SUM(AU13:BC13)+BN13+BO13 -> 1252.4582 | AT13: =AR13-AS13 -> 0 | AU13: =D13/G13*Z13 -> 0 | AV13: =E13/G13*Z13*-1 -> -13.971617 | AW13: =F13/G13*Y13 -> 0 | AX13: =1/G13*V13 -> 414.04082 | AY13: =H13/G13*AH13 -> -7.7852153 | AZ13: =I13/G13*AH13*-1 -> 0 | BA13: =L13/G13/(0.9*8760) -> 236.76831 | BB13: =M13/G13/(0.9*8760) -> 129.5863 | BC13: =N13/G13 -> 31.564969 | BD13: =BZ13+CA13+CB13 -> 0.876454 | BE13: =(Q13+R13)*-1*J13/G13 -> 0 | BF13: =BD13*Q13 -> 87.56941 | BG13: =BZ13+CA13 -> 0.876454 | BH13: =R13*J13*-1/G13 -> 0 | BI13: =BG13*Q13 -> 87.56941 | BJ13: =SUM(BY13:CC13) -> 4.626558 | BK13: =(Q13+R13)*-1*J13/G13 -> 0 | BL13: =BJ13*Q13 -> 462.25466 | BM13: =BY13+BZ13+CA13+CC13 -> 4.626558 | BN13: =J13/G13*R13*-1 -> 0 | BO13: =Q13*BM13 -> 462.25466 | BQ13: 3.14 | BR13: 0.221811 | BS13: 0.18104824 | BU13: =1/G13*BR13 -> 4.1770824 | BV13: =H13/G13*BS13 -> 0.44947553 | BW13: =BU13+BV13 -> 4.626558 | BY13: =BQ13 -> 3.14 | BZ13: =I13/G13*BS13 -> 0 | CA13: =K13/G13 -> 0.876454 | CB13: =J13/G13 -> 0 | CC13: =BW13-SUM(BY13:CB13) -> 0.61010397 | CD13: =SUM(BY13:CC13) -> 4.626558 | CF13: =CD13-BW13 -> 0
B14: CA_TSC+CC90:H2 | C14: Ethane | D14: 0 | E14: 0.15985314 | F14: 0.0093887367 | G14: 0.053101897 | H14: 0.13183229 | I14: 0 | J14: 0.041887233 | K14: 0.004654137 | L14: 106900.97 | M14: 58510.186 | N14: 1.8076604 | O14: =CC14/0.22/14 -> 0.1980857 | Q14: 99.913298 | R14: -5.387721 | S14: 69.443859 | T14: 44.089523 | U14: 38.115627 | V14: 21.986353 | Y14: 19.219858 | Z14: 4.641256 | AH14: -3.135876 | AI14: -4.519557 | AJ14: 796.73601 | AK14: 0 | AM14: =B14 -> CA_TSC+CC90:H2 | AN14: =C14 -> Ethane | AO14: =SUM(AU14:BC14)+BE14+BF14 -> 837.83138 | AP14: =SUM(AU14:BC14)+BH14+BI14 -> 837.83138 | AQ14: =AO14-AP14 -> 0 | AR14: =SUM(AU14:BC14)+BK14+BL14 -> 1212.5166 | AS14: =SUM(AU14:BC14)+BN14+BO14 -> 1212.5166 | AT14: =AR14-AS14 -> 0 | AU14: =D14/G14*Z14 -> 0 | AV14: =E14/G14*Z14*-1 -> -13.971617 | AW14: =F14/G14*Y14 -> 3.3981872 | AX14: =1/G14*V14 -> 414.04082 | AY14: =H14/G14*AH14 -> -7.7852153 | AZ14: =I14/G14*AH14*-1 -> 0 | BA14: =L14/G14/(0.9*8760) -> 255.34362 | BB14: =M14/G14/(0.9*8760) -> 139.7574 | BC14: =N14/G14 -> 34.041353 | BD14: =BZ14+CA14+CB14 -> 0.876454 | BE14: =(Q14+R14)*-1*J14/G14 -> -74.562588 | BF14: =BD14*Q14 -> 87.56941 | BG14: =BZ14+CA14 -> 0.0876454 | BH14: =R14*J14*-1/G14 -> 4.2498807 | BI14: =BG14*Q14 -> 8.756941 | BJ14: =SUM(BY14:CC14) -> 4.626558 | BK14: =(Q14+R14)*-1*J14/G14 -> -74.562588 | BL14: =BJ14*Q14 -> 462.25466 | BM14: =BY14+BZ14+CA14+CC14 -> 3.8377494 | BN14: =J14/G14*R14*-1 -> 4.2498807 | BO14: =Q14*BM14 -> 383.4422 | BQ14: 3.14 | BR14: 0.221811 | BS14: 0.18104824 | BU14: =1/G14*BR14 -> 4.1770824 | BV14: =H14/G14*BS14 -> 0.44947553 | BW14: =BU14+BV14 -> 4.626558 | BY14: =BQ14 -> 3.14 | BZ14: =I14/G14*BS14 -> 0 | CA14: =K14/G14 -> 0.0876454 | CB14: =J14/G14 -> 0.7888086 | CC14: =BW14-SUM(BY14:CB14) -> 0.61010397 | CD14: =SUM(BY14:CC14) -> 4.626558 | CF14: =CD14-BW14 -> 0
... B65: NE_ESC | C65: Ethane | D65: 0 | E65: 0.15985314 | F65: 0.19138279 | G65: 0.053101897 | H65: 0 | I65: 0.1181425 | J65: 0 | K65: 0.0012838759 | L65: 131324.11 | M65: 71875.354 | N65: 2.2206477 | O65: =CC65/0.22/14 -> 0.1980857 | Q65: 99.913298 | R65: -21.727401 | S65: 66.936657 | T65: 41.693039 | U65: 41.333943 | V65: 21.986353 | Y65: 20.978032 | Z65: 12.546751 | AH65: 5.888729 | AI65: 0 | AJ65: 796.73601 | AK65: 0 | AM65: =B65 -> NE_ESC | AN65: =C65 -> Ethane | AO65: =SUM(AU65:BC65)+BE65+BF65 -> 1008.6177 | AP65: =SUM(AU65:BC65)+BH65+BI65 -> 1008.6177 | AQ65: =AO65-AP65 -> 0 | AR65: =SUM(AU65:BC65)+BK65+BL65 -> 1383.3029 | AS65: =SUM(AU65:BC65)+BN65+BO65 -> 1383.3029 | AT65: =AR65-AS65 -> 0 | AU65: =D65/G65*Z65 -> 0 | AV65: =E65/G65*Z65*-1 -> -37.769603 | AW65: =F65/G65*Y65 -> 75.606232 | AX65: =1/G65*V65 -> 414.04082 | AY65: =H65/G65*AH65 -> 0 | AZ65: =I65/G65*AH65*-1 -> -13.101399 | BA65: =L65/G65/(0.9*8760) -> 313.68072 | BB65: =M65/G65/(0.9*8760) -> 171.68144 | BC65: =N65/G65 -> 41.818614 | BD65: =BZ65+CA65+CB65 -> 0.42697847 | BE65: =(Q65+R65)*-1*J65/G65 -> 0 | BF65: =BD65*Q65 -> 42.660827 | BG65: =BZ65+CA65 -> 0.42697847 | BH65: =R65*J65*-1/G65 -> 0 | BI65: =BG65*Q65 -> 42.660827 | BJ65: =SUM(BY65:CC65) -> 4.1770824 | BK65: =(Q65+R65)*-1*J65/G65 -> 0 | BL65: =BJ65*Q65 -> 417.34608 | BM65: =BY65+BZ65+CA65+CC65 -> 4.1770824 | BN65: =J65/G65*R65*-1 -> 0 | BO65: =Q65*BM65 -> 417.34608 | BQ65: 3.14 | BR65: 0.221811 | BS65: 0.18104824 | BU65: =1/G65*BR65 -> 4.1770824 | BV65: =H65/G65*BS65 -> 0 | BW65: =BU65+BV65 -> 4.1770824 | BY65: =BQ65 -> 3.14 | BZ65: =I65/G65*BS65 -> 0.40280088 | CA65: =K65/G65 -> 0.02417759 | CB65: =J65/G65 -> 0 | CC65: =BW65-SUM(BY65:CB65) -> 0.61010397 | CD65: =SUM(BY65:CC65) -> 4.1770824 | CF65: =CD65-BW65 -> 0

Sheet lc_summary_seq
B1: LCOE for steam/electric cracker ($/GJ-ethylene) - CHEMICALS SEQUESTRATION | S1: Assumptions
B2: id_LC | C2: h2_consumption | D2: h2_production | E2: elec_consumption | F2: ethane_consumption | G2: natgas_consumption | H2: natgas_production | I2: investment_cost | J2: fixed_om_cost | K2: variable_om_cost | L2: modified capture cost | M2: modified emissions cost | N2: CI | O2: LCOE ($/t-ethylene) | P2: LCOE ($/GJ-ethylene) | Q2: CHECK LCOE ($/GJ-ethylene) | S2: Ethylene LHV | T2: 45.6 | U2: GJ/t-ethylene
B3: =lc_detailed!AM3 -> CA_TSC | C3: =lc_detailed!AU3/$T$2 -> 0 | D3: =lc_detailed!AV3/$T$2 -> 0 | E3: =lc_detailed!AW3/$T$2 -> 0 | F3: =lc_detailed!AX3/$T$2 -> 9.0798426 | G3: =lc_detailed!AY3/$T$2 -> -0.029399663 | H3: =lc_detailed!AZ3/$T$2 -> 0 | I3: =lc_detailed!BA3/$T$2 -> 5.1922874 | J3: =lc_detailed!BB3/$T$2 -> 2.8418048 | K3: =lc_detailed!BC3/$T$2 -> 0.69221424 | L3: =lc_detailed!BE3/$T$2 -> 0 | M3: =lc_detailed!BF3/$T$2 -> 1.1051348 | N3: =lc_detailed!BD3 -> 0.50437877 | O3: =lc_detailed!AO3 -> 861.01392 | P3: =O3/$T$2 -> 18.881884 | Q3: =SUM(C3:M3) -> 18.881884
B4: =lc_detailed!AM4 -> SW_TSC | C4: =lc_detailed!AU4/$T$2 -> 0 | D4: =lc_detailed!AV4/$T$2 -> 0 | E4: =lc_detailed!AW4/$T$2 -> 0 | F4: =lc_detailed!AX4/$T$2 -> 9.0798426 | G4: =lc_detailed!AY4/$T$2 -> -0.01198034 | H4: =lc_detailed!AZ4/$T$2 -> 0 | I4: =lc_detailed!BA4/$T$2 -> 5.1922874 | J4: =lc_detailed!BB4/$T$2 -> 2.8418048 | K4: =lc_detailed!BC4/$T$2 -> 0.69221424 | L4: =lc_detailed!BE4/$T$2 -> 0 | M4: =lc_detailed!BF4/$T$2 -> 1.1051348 | N4: =lc_detailed!BD4 -> 0.50437877 | O4: =lc_detailed!AO4 -> 861.80824 | P4: =O4/$T$2 -> 18.899304 | Q4: =SUM(C4:M4) -> 18.899304
B5: =lc_detailed!AM5 -> NW_TSC | C5: =lc_detailed!AU5/$T$2 -> 0 | D5: =lc_detailed!AV5/$T$2 -> 0 | E5: =lc_detailed!AW5/$T$2 -> 0 | F5: =lc_detailed!AX5/$T$2 -> 9.0798426 | G5: =lc_detailed!AY5/$T$2 -> -0.022863492 | H5: =lc_detailed!AZ5/$T$2 -> 0 | I5: =lc_detailed!BA5/$T$2 -> 5.1922874 | J5: =lc_detailed!BB5/$T$2 -> 2.8418048 | K5: =lc_detailed!BC5/$T$2 -> 0.69221424 | L5: =lc_detailed!BE5/$T$2 -> 0 | M5: =lc_detailed!BF5/$T$2 -> 1.1051348 | N5: =lc_detailed!BD5 -> 0.50437877 | O5: =lc_detailed!AO5 -> 861.31197 | P5: =O5/$T$2 -> 18.88842 | Q5: =SUM(C5:M5) -> 18.88842
B6: =lc_detailed!AM6 -> TX_TSC | C6: =lc_detailed!AU6/$T$2 -> 0 | D6: =lc_detailed!AV6/$T$2 -> 0 | E6: =lc_detailed!AW6/$T$2 -> 0 | F6: =lc_detailed!AX6/$T$2 -> 9.0798426 | G6: =lc_detailed!AY6/$T$2 -> -0.013886528 | H6: =lc_detailed!AZ6/$T$2 -> 0 | I6: =lc_detailed!BA6/$T$2 -> 5.1922874 | J6: =lc_detailed!BB6/$T$2 -> 2.8418048 | K6: =lc_detailed!BC6/$T$2 -> 0.69221424 | L6: =lc_detailed!BE6/$T$2 -> 0 | M6: =lc_detailed!BF6/$T$2 -> 1.1051348 | N6: =lc_detailed!BD6 -> 0.50437877 | O6: =lc_detailed!AO6 -> 861.72132 | P6: =O6/$T$2 -> 18.897397 | Q6: =SUM(C6:M6) -> 18.897397
B7: =lc_detailed!AM7 -> NCEN_TSC | C7: =lc_detailed!AU7/$T$2 -> 0 | D7: =lc_detailed!AV7/$T$2 -> 0 | E7: =lc_detailed!AW7/$T$2 -> 0 | F7: =lc_detailed!AX7/$T$2 -> 9.0798426 | G7: =lc_detailed!AY7/$T$2 -> -0.007732511 | H7: =lc_detailed!AZ7/$T$2 -> 0 | I7: =lc_detailed!BA7/$T$2 -> 5.1922874 | J7: =lc_detailed!BB7/$T$2 -> 2.8418048 | K7: =lc_detailed!BC7/$T$2 -> 0.69221424 | L7: =lc_detailed!BE7/$T$2 -> 0 | M7: =lc_detailed!BF7/$T$2 -> 1.1051348 | N7: =lc_detailed!BD7 -> 0.50437877 | O7: =lc_detailed!AO7 -> 862.00194 | P7: =O7/$T$2 -> 18.903551 | Q7: =SUM(C7:M7) -> 18.903551
B8: =lc_detailed!AM8 -> CEN_TSC | C8: =lc_detailed!AU8/$T$2 -> 0 | D8: =lc_detailed!AV8/$T$2 -> 0 | E8: =lc_detailed!AW8/$T$2 -> 0 | F8: =lc_detailed!AX8/$T$2 -> 9.0798426 | G8: =lc_detailed!AY8/$T$2 -> -0.013420286 | H8: =lc_detailed!AZ8/$T$2 -> 0 | I8: =lc_detailed!BA8/$T$2 -> 5.1922874 | J8: =lc_detailed!BB8/$T$2 -> 2.8418048 | K8: =lc_detailed!BC8/$T$2 -> 0.69221424 | L8: =lc_detailed!BE8/$T$2 -> 0 | M8: =lc_detailed!BF8/$T$2 -> 1.1051348 | N8: =lc_detailed!BD8 -> 0.50437877 | O8: =lc_detailed!AO8 -> 861.74258 | P8: =O8/$T$2 -> 18.897864 | Q8: =SUM(C8:M8) -> 18.897864
B9: =lc_detailed!AM9 -> SE_TSC | C9: =lc_detailed!AU9/$T$2 -> 0 | D9: =lc_detailed!AV9/$T$2 -> 0 | E9: =lc_detailed!AW9/$T$2 -> 0 | F9: =lc_detailed!AX9/$T$2 -> 9.0798426 | G9: =lc_detailed!AY9/$T$2 -> -0.013616107 | H9: =lc_detailed!AZ9/$T$2 -> 0 | I9: =lc_detailed!BA9/$T$2 -> 5.1922874 | J9: =lc_detailed!BB9/$T$2 -> 2.8418048 | K9: =lc_detailed!BC9/$T$2 -> 0.69221424 | L9: =lc_detailed!BE9/$T$2 -> 0 | M9: =lc_detailed!BF9/$T$2 -> 1.1051348 | N9: =lc_detailed!BD9 -> 0.50437877 | O9: =lc_detailed!AO9 -> 861.73365 | P9: =O9/$T$2 -> 18.897668 | Q9: =SUM(C9:M9) -> 18.897668
B10: =lc_detailed!AM10 -> MIDAT_TSC | C10: =lc_detailed!AU10/$T$2 -> 0 | D10: =lc_detailed!AV10/$T$2 -> 0 | E10: =lc_detailed!AW10/$T$2 -> 0 | F10: =lc_detailed!AX10/$T$2 -> 9.0798426 | G10: =lc_detailed!AY10/$T$2 -> -0.0087210762 | H10: =lc_detailed!AZ10/$T$2 -> 0 | I10: =lc_detailed!BA10/$T$2 -> 5.1922874 | J10: =lc_detailed!BB10/$T$2 -> 2.8418048 | K10: =lc_detailed!BC10/$T$2 -> 0.69221424 | L10: =lc_detailed!BE10/$T$2 -> 0 | M10: =lc_detailed!BF10/$T$2 -> 1.1051348 | N10: =lc_detailed!BD10 -> 0.50437877 | O10: =lc_detailed!AO10 -> 861.95686 | P10: =O10/$T$2 -> 18.902563 | Q10: =SUM(C10:M10) -> 18.902563
B11: =lc_detailed!AM11 -> NE_TSC | C11: =lc_detailed!AU11/$T$2 -> 0 | D11: =lc_detailed!AV11/$T$2 -> 0 | E11: =lc_detailed!AW11/$T$2 -> 0 | F11: =lc_detailed!AX11/$T$2 -> 9.0798426 | G11: =lc_detailed!AY11/$T$2 -> 0.055208385 | H11: =lc_detailed!AZ11/$T$2 -> 0 | I11: =lc_detailed!BA11/$T$2 -> 5.1922874 | J11: =lc_detailed!BB11/$T$2 -> 2.8418048 | K11: =lc_detailed!BC11/$T$2 -> 0.69221424 | L11: =lc_detailed!BE11/$T$2 -> 0 | M11: =lc_detailed!BF11/$T$2 -> 1.1051348 | N11: =lc_detailed!BD11 -> 0.50437877 | O11: =lc_detailed!AO11 -> 864.87205 | P11: =O11/$T$2 -> 18.966492 | Q11: =SUM(C11:M11) -> 18.966492
B12: =lc_detailed!AM12 -> CA_TSC+CC90 | C12: =lc_detailed!AU12/$T$2 -> 0 | D12: =lc_detailed!AV12/$T$2 -> 0 | E12: =lc_detailed!AW12/$T$2 -> 0.063919178 | F12: =lc_detailed!AX12/$T$2 -> 9.0798426 | G12: =lc_detailed!AY12/$T$2 -> -0.029399663 | H12: =lc_detailed!AZ12/$T$2 -> 0 | I12: =lc_detailed!BA12/$T$2 -> 5.5982891 | J12: =lc_detailed!BB12/$T$2 -> 3.0641326 | K12: =lc_detailed!BC12/$T$2 -> 0.7463407 | L12: =lc_detailed!BE12/$T$2 -> -0.94098738 | M12: =lc_detailed!BF12/$T$2 -> 1.1051348 | N12: =lc_detailed!BD12 -> 0.50437877 | O12: =lc_detailed!AO12 -> 852.1396 | P12: =O12/$T$2 -> 18.687272 | Q12: =SUM(C12:M12) -> 18.687272
B13: =lc_detailed!AM13 -> CA_TSC:H2 | C13: =lc_detailed!AU13/$T$2 -> 0 | D13: =lc_detailed!AV13/$T$2 -> -0.30639511 | E13: =lc_detailed!AW13/$T$2 -> 0 | F13: =lc_detailed!AX13/$T$2 -> 9.0798426 | G13: =lc_detailed!AY13/$T$2 -> -0.17072841 | H13: =lc_detailed!AZ13/$T$2 -> 0 | I13: =lc_detailed!BA13/$T$2 -> 5.1922874 | J13: =lc_detailed!BB13/$T$2 -> 2.8418048 | K13: =lc_detailed!BC13/$T$2 -> 0.69221424 | L13: =lc_detailed!BE13/$T$2 -> 0 | M13: =lc_detailed!BF13/$T$2 -> 1.9203818 | N13: =lc_detailed!BD13 -> 0.876454 | O13: =lc_detailed!AO13 -> 877.77298 | P13: =O13/$T$2 -> 19.249407 | Q13: =SUM(C13:M13) -> 19.249407
B14: =lc_detailed!AM14 -> CA_TSC+CC90:H2 | C14: =lc_detailed!AU14/$T$2 -> 0 | D14: =lc_detailed!AV14/$T$2 -> -0.30639511 | E14: =lc_detailed!AW14/$T$2 -> 0.074521649 | F14: =lc_detailed!AX14/$T$2 -> 9.0798426 | G14: =lc_detailed!AY14/$T$2 -> -0.17072841 | H14: =lc_detailed!AZ14/$T$2 -> 0 | I14: =lc_detailed!BA14/$T$2 -> 5.5996408 | J14: =lc_detailed!BB14/$T$2 -> 3.0648553 | K14: =lc_detailed!BC14/$T$2 -> 0.7465209 | L14: =lc_detailed!BE14/$T$2 -> -1.6351445 | M14: =lc_detailed!BF14/$T$2 -> 1.9203818 | N14: =lc_detailed!BD14 -> 0.876454 | O14: =lc_detailed!AO14 -> 837.83138 | P14: =O14/$T$2 -> 18.373495 | Q14: =SUM(C14:M14) -> 18.373495
... B65: =lc_detailed!AM65 -> NE_ESC | C65: =lc_detailed!AU65/$T$2 -> 0 | D65: =lc_detailed!AV65/$T$2 -> -0.82828077 | E65: =lc_detailed!AW65/$T$2 -> 1.6580314 | F65: =lc_detailed!AX65/$T$2 -> 9.0798426 | G65: =lc_detailed!AY65/$T$2 -> 0 | H65: =lc_detailed!AZ65/$T$2 -> -0.28731138 | I65: =lc_detailed!BA65/$T$2 -> 6.8789632 | J65: =lc_detailed!BB65/$T$2 -> 3.7649438 | K65: =lc_detailed!BC65/$T$2 -> 0.91707486 | L65: =lc_detailed!BE65/$T$2 -> 0 | M65: =lc_detailed!BF65/$T$2 -> 0.93554446 | N65: =lc_detailed!BD65 -> 0.42697847 | O65: =lc_detailed!AO65 -> 1008.6177 | P65: =O65/$T$2 -> 22.118808 | Q65: =SUM(C65:M65) -> 22.118808

Sheet lc_summary_noseq
B1: LCOE for steam/electric cracker ($/GJ-ethylene) - NO CHEMICALS SEQUESTRATION | S1: Assumptions
B2: id_LC | C2: h2_consumption | D2: h2_production | E2: elec_consumption | F2: ethane_consumption | G2: natgas_consumption | H2: natgas_production | I2: investment_cost | J2: fixed_om_cost | K2: variable_om_cost | L2: modified capture cost | M2: modified emissions cost | N2: CI | O2: LCOE ($/t-ethylene) | P2: LCOE ($/GJ-ethylene) | Q2: CHECK LCOE ($/GJ-ethylene) | S2: Ethylene LHV | T2: 45.6 | U2: GJ/t-ethylene
B3: =lc_detailed!AM3 -> CA_TSC | C3: =lc_detailed!AU3/$T$2 -> 0 | D3: =lc_detailed!AV3/$T$2 -> 0 | E3: =lc_detailed!AW3/$T$2 -> 0 | F3: =lc_detailed!AX3/$T$2 -> 9.0798426 | G3: =lc_detailed!AY3/$T$2 -> -0.029399663 | H3: =lc_detailed!AZ3/$T$2 -> 0 | I3: =lc_detailed!BA3/$T$2 -> 5.1922874 | J3: =lc_detailed!BB3/$T$2 -> 2.8418048 | K3: =lc_detailed!BC3/$T$2 -> 0.69221424 | L3: =lc_detailed!BK3/$T$2 -> 0 | M3: =lc_detailed!BL3/$T$2 -> 9.3219167 | N3: =lc_detailed!BJ3 -> 4.2544827 | O3: =lc_detailed!AR3 -> 1235.6992 | P3: =O3/$T$2 -> 27.098666 | Q3: =SUM(C3:M3) -> 27.098666
B4: =lc_detailed!AM4 -> SW_TSC | C4: =lc_detailed!AU4/$T$2 -> 0 | D4: =lc_detailed!AV4/$T$2 -> 0 | E4: =lc_detailed!AW4/$T$2 -> 0 | F4: =lc_detailed!AX4/$T$2 -> 9.0798426 | G4: =lc_detailed!AY4/$T$2 -> -0.01198034 | H4: =lc_detailed!AZ4/$T$2 -> 0 | I4: =lc_detailed!BA4/$T$2 -> 5.1922874 | J4: =lc_detailed!BB4/$T$2 -> 2.8418048 | K4: =lc_detailed!BC4/$T$2 -> 0.69221424 | L4: =lc_detailed!BK4/$T$2 -> 0 | M4: =lc_detailed!BL4/$T$2 -> 9.3219167 | N4: =lc_detailed!BJ4 -> 4.2544827 | O4: =lc_detailed!AR4 -> 1236.4935 | P4: =O4/$T$2 -> 27.116085 | Q4: =SUM(C4:M4) -> 27.116085
B5: =lc_detailed!AM5 -> NW_TSC | C5: =lc_detailed!AU5/$T$2 -> 0 | D5: =lc_detailed!AV5/$T$2 -> 0 | E5: =lc_detailed!AW5/$T$2 -> 0 | F5: =lc_detailed!AX5/$T$2 -> 9.0798426 | G5: =lc_detailed!AY5/$T$2 -> -0.022863492 | H5: =lc_detailed!AZ5/$T$2 -> 0 | I5: =lc_detailed!BA5/$T$2 -> 5.1922874 | J5: =lc_detailed!BB5/$T$2 -> 2.8418048 | K5: =lc_detailed!BC5/$T$2 -> 0.69221424 | L5: =lc_detailed!BK5/$T$2 -> 0 | M5: =lc_detailed!BL5/$T$2 -> 9.3219167 | N5: =lc_detailed!BJ5 -> 4.2544827 | O5: =lc_detailed!AR5 -> 1235.9972 | P5: =O5/$T$2 -> 27.105202 | Q5: =SUM(C5:M5) -> 27.105202
B6: =lc_detailed!AM6 -> TX_TSC | C6: =lc_detailed!AU6/$T$2 -> 0 | D6: =lc_detailed!AV6/$T$2 -> 0 | E6: =lc_detailed!AW6/$T$2 -> 0 | F6: =lc_detailed!AX6/$T$2 -> 9.0798426 | G6: =lc_detailed!AY6/$T$2 -> -0.013886528 | H6: =lc_detailed!AZ6/$T$2 -> 0 | I6: =lc_detailed!BA6/$T$2 -> 5.1922874 | J6: =lc_detailed!BB6/$T$2 -> 2.8418048 | K6: =lc_detailed!BC6/$T$2 -> 0.69221424 | L6: =lc_detailed!BK6/$T$2 -> 0 | M6: =lc_detailed!BL6/$T$2 -> 9.3219167 | N6: =lc_detailed!BJ6 -> 4.2544827 | O6: =lc_detailed!AR6 -> 1236.4066 | P6: =O6/$T$2 -> 27.114179 | Q6: =SUM(C6:M6) -> 27.114179
B7: =lc_detailed!AM7 -> NCEN_TSC | C7: =lc_detailed!AU7/$T$2 -> 0 | D7: =lc_detailed!AV7/$T$2 -> 0 | E7: =lc_detailed!AW7/$T$2 -> 0 | F7: =lc_detailed!AX7/$T$2 -> 9.0798426 | G7: =lc_detailed!AY7/$T$2 -> -0.007732511 | H7: =lc_detailed!AZ7/$T$2 -> 0 | I7: =lc_detailed!BA7/$T$2 -> 5.1922874 | J7: =lc_detailed!BB7/$T$2 -> 2.8418048 | K7: =lc_detailed!BC7/$T$2 -> 0.69221424 | L7: =lc_detailed!BK7/$T$2 -> 0 | M7: =lc_detailed!BL7/$T$2 -> 9.3219167 | N7: =lc_detailed!BJ7 -> 4.2544827 | O7: =lc_detailed!AR7 -> 1236.6872 | P7: =O7/$T$2 -> 27.120333 | Q7: =SUM(C7:M7) -> 27.120333
B8: =lc_detailed!AM8 -> CEN_TSC | C8: =lc_detailed!AU8/$T$2 -> 0 | D8: =lc_detailed!AV8/$T$2 -> 0 | E8: =lc_detailed!AW8/$T$2 -> 0 | F8: =lc_detailed!AX8/$T$2 -> 9.0798426 | G8: =lc_detailed!AY8/$T$2 -> -0.013420286 | H8: =lc_detailed!AZ8/$T$2 -> 0 | I8: =lc_detailed!BA8/$T$2 -> 5.1922874 | J8: =lc_detailed!BB8/$T$2 -> 2.8418048 | K8: =lc_detailed!BC8/$T$2 -> 0.69221424 | L8: =lc_detailed!BK8/$T$2 -> 0 | M8: =lc_detailed!BL8/$T$2 -> 9.3219167 | N8: =lc_detailed!BJ8 -> 4.2544827 | O8: =lc_detailed!AR8 -> 1236.4278 | P8: =O8/$T$2 -> 27.114645 | Q8: =SUM(C8:M8) -> 27.114645
B9: =lc_detailed!AM9 -> SE_TSC | C9: =lc_detailed!AU9/$T$2 -> 0 | D9: =lc_detailed!AV9/$T$2 -> 0 | E9: =lc_detailed!AW9/$T$2 -> 0 | F9: =lc_detailed!AX9/$T$2 -> 9.0798426 | G9: =lc_detailed!AY9/$T$2 -> -0.013616107 | H9: =lc_detailed!AZ9/$T$2 -> 0 | I9: =lc_detailed!BA9/$T$2 -> 5.1922874 | J9: =lc_detailed!BB9/$T$2 -> 2.8418048 | K9: =lc_detailed!BC9/$T$2 -> 0.69221424 | L9: =lc_detailed!BK9/$T$2 -> 0 | M9: =lc_detailed!BL9/$T$2 -> 9.3219167 | N9: =lc_detailed!BJ9 -> 4.2544827 | O9: =lc_detailed!AR9 -> 1236.4189 | P9: =O9/$T$2 -> 27.11445 | Q9: =SUM(C9:M9) -> 27.11445
B10: =lc_detailed!AM10 -> MIDAT_TSC | C10: =lc_detailed!AU10/$T$2 -> 0 | D10: =lc_detailed!AV10/$T$2 -> 0 | E10: =lc_detailed!AW10/$T$2 -> 0 | F10: =lc_detailed!AX10/$T$2 -> 9.0798426 | G10: =lc_detailed!AY10/$T$2 -> -0.0087210762 | H10: =lc_detailed!AZ10/$T$2 -> 0 | I10: =lc_detailed!BA10/$T$2 -> 5.1922874 | J10: =lc_detailed!BB10/$T$2 -> 2.8418048 | K10: =lc_detailed!BC10/$T$2 -> 0.69221424 | L10: =lc_detailed!BK10/$T$2 -> 0 | M10: =lc_detailed!BL10/$T$2 -> 9.3219167 | N10: =lc_detailed!BJ10 -> 4.2544827 | O10: =lc_detailed!AR10 -> 1236.6421 | P10: =O10/$T$2 -> 27.119345 | Q10: =SUM(C10:M10) -> 27.119345
B11: =lc_detailed!AM11 -> NE_TSC | C11: =lc_detailed!AU11/$T$2 -> 0 | D11: =lc_detailed!AV11/$T$2 -> 0 | E11: =lc_detailed!AW11/$T$2 -> 0 | F11: =lc_detailed!AX11/$T$2 -> 9.0798426 | G11: =lc_detailed!AY11/$T$2 -> 0.055208385 | H11: =lc_detailed!AZ11/$T$2 -> 0 | I11: =lc_detailed!BA11/$T$2 -> 5.1922874 | J11: =lc_detailed!BB11/$T$2 -> 2.8418048 | K11: =lc_detailed!BC11/$T$2 -> 0.69221424 | L11: =lc_detailed!BK11/$T$2 -> 0 | M11: =lc_detailed!BL11/$T$2 -> 9.3219167 | N11: =lc_detailed!BJ11 -> 4.2544827 | O11: =lc_detailed!AR11 -> 1239.5573 | P11: =O11/$T$2 -> 27.183274 | Q11: =SUM(C11:M11) -> 27.183274
B12: =lc_detailed!AM12 -> CA_TSC+CC90 | C12: =lc_detailed!AU12/$T$2 -> 0 | D12: =lc_detailed!AV12/$T$2 -> 0 | E12: =lc_detailed!AW12/$T$2 -> 0.063919178 | F12: =lc_detailed!AX12/$T$2 -> 9.0798426 | G12: =lc_detailed!AY12/$T$2 -> -0.029399663 | H12: =lc_detailed!AZ12/$T$2 -> 0 | I12: =lc_detailed!BA12/$T$2 -> 5.5982891 | J12: =lc_detailed!BB12/$T$2 -> 3.0641326 | K12: =lc_detailed!BC12/$T$2 -> 0.7463407 | L12: =lc_detailed!BK12/$T$2 -> -0.94098738 | M12: =lc_detailed!BL12/$T$2 -> 9.3219167 | N12: =lc_detailed!BJ12 -> 4.2544827 | O12: =lc_detailed!AR12 -> 1226.8249 | P12: =O12/$T$2 -> 26.904054 | Q12: =SUM(C12:M12) -> 26.904054
B13: =lc_detailed!AM13 -> CA_TSC:H2 | C13: =lc_detailed!AU13/$T$2 -> 0 | D13: =lc_detailed!AV13/$T$2 -> -0.30639511 | E13: =lc_detailed!AW13/$T$2 -> 0 | F13: =lc_detailed!AX13/$T$2 -> 9.0798426 | G13: =lc_detailed!AY13/$T$2 -> -0.17072841 | H13: =lc_detailed!AZ13/$T$2 -> 0 | I13: =lc_detailed!BA13/$T$2 -> 5.1922874 | J13: =lc_detailed!BB13/$T$2 -> 2.8418048 | K13: =lc_detailed!BC13/$T$2 -> 0.69221424 | L13: =lc_detailed!BK13/$T$2 -> 0 | M13: =lc_detailed!BL13/$T$2 -> 10.137164 | N13: =lc_detailed!BJ13 -> 4.626558 | O13: =lc_detailed!AR13 -> 1252.4582 | P13: =O13/$T$2 -> 27.466189 | Q13: =SUM(C13:M13) -> 27.466189
B14: =lc_detailed!AM14 -> CA_TSC+CC90:H2 | C14: =lc_detailed!AU14/$T$2 -> 0 | D14: =lc_detailed!AV14/$T$2 -> -0.30639511 | E14: =lc_detailed!AW14/$T$2 -> 0.074521649 | F14: =lc_detailed!AX14/$T$2 -> 9.0798426 | G14: =lc_detailed!AY14/$T$2 -> -0.17072841 | H14: =lc_detailed!AZ14/$T$2 -> 0 | I14: =lc_detailed!BA14/$T$2 -> 5.5996408 | J14: =lc_detailed!BB14/$T$2 -> 3.0648553 | K14: =lc_detailed!BC14/$T$2 -> 0.7465209 | L14: =lc_detailed!BK14/$T$2 -> -1.6351445 | M14: =lc_detailed!BL14/$T$2 -> 10.137164 | N14: =lc_detailed!BJ14 -> 4.626558 | O14: =lc_detailed!AR14 -> 1212.5166 | P14: =O14/$T$2 -> 26.590277 | Q14: =SUM(C14:M14) -> 26.590277
... B65: =lc_detailed!AM65 -> NE_ESC | C65: =lc_detailed!AU65/$T$2 -> 0 | D65: =lc_detailed!AV65/$T$2 -> -0.82828077 | E65: =lc_detailed!AW65/$T$2 -> 1.6580314 | F65: =lc_detailed!AX65/$T$2 -> 9.0798426 | G65: =lc_detailed!AY65/$T$2 -> 0 | H65: =lc_detailed!AZ65/$T$2 -> -0.28731138 | I65: =lc_detailed!BA65/$T$2 -> 6.8789632 | J65: =lc_detailed!BB65/$T$2 -> 3.7649438 | K65: =lc_detailed!BC65/$T$2 -> 0.91707486 | L65: =lc_detailed!BK65/$T$2 -> 0 | M65: =lc_detailed!BL65/$T$2 -> 9.1523264 | N65: =lc_detailed!BJ65 -> 4.1770824 | O65: =lc_detailed!AR65 -> 1383.3029 | P65: =O65/$T$2 -> 30.33559 | Q65: =SUM(C65:M65) -> 30.33559
