Workbook

Sheet lc_detailed
B2: Ethanol Upgrade Asset Parameters (normalized by MWh ethanol) | D2: Ethanol feedstock asset | Q2: Ethanol Production Asset Parameters (normalized by commodity feedstock) | AD2: Duals | AZ2: LCOE for assets with ethane capacity ($/t-ethylene) | BB2: SEQ - CI | BC2: SEQ - CREDIT | BE2: NO SEQ - CI | BF2: NO SEQ - CREDIT | BU2: CHEM SEQUESTRATION - CARBON INTENSITY | BX2: CHEM SEQUESTRATION - CREDIT | CA2: NO CHEM SEQUESTRATION - CARBON INTENSITY | CD2: NO CHEM SEQUESTRATION - CREDIT | CH2: Ethanol Production LCOE parameters ($/t-ethylene) | CS2: Carbon Content | CX2: Carbon Inputs - Ethanol Production | CZ2: Carbon Inputs - Ethanol Dehydration | DD2: Carbon Outputs - Ethanol Production | DF2: Carbon Outputs - Ethanol Dehydration | DJ2: Sanity Checks | DL2: Asset Parameters (normalized by commodity feedstock)
B3: id | C3: commodity | D3: production_asset | E3: id_name | F3: h2_consumption (MWh/MWh-ethanol) | G3: elec_consumption (MWh/MWh-ethanol) | H3: ethylene_production (t-ethylene/MWh-ethanol) | I3: natgas_consumption (MWh/MWh-ethanol) | J3: capture_rate (t-CO2/MWh-ethanol) | K3: emission_rate (t-CO2/MWh-ethanol) | L3: calculated_emission_rate (t-CO2/MWh-ethanol) | M3: investment_cost ($/yr per MW ethanol) | N3: fixed_om_cost ($/yr per MW ethanol) | O3: variable_om_cost ($/MWh-ethanol) | Q3: id_bioethanol | R3: commodity_bioethanol | S3: elec_production (MWh/t-bio) | T3: elec_consumption (MWh/t-bio) | U3: ethanol_production (MWh-ethanol/t-bio) | V3: natgas_consumption (MWh/t-bio) | W3: co2_biomass_content (t-CO2/t-bio) | X3: capture_rate (t-CO2/t-bio) | Y3: emission_rate (t-CO2/t-bio) | Z3: investment_cost ($/yr per t-bio/hr) | AA3: fixed_om_cost ($/yr per t-bio/hr) | AB3: variable_om_cost ($/t-bio) | AD3: co2_sink ($/t) | AE3: co2_captured ($/t) | AF3: bioherb_supply ($/t) | AG3: biowood_supply ($/t) | AH3: bioagri_supply ($/t) | AI3: biocorn_supply ($/t) | AJ3: ethanol_balance ($/MWh) | AK3: ethanol_demand ($/MWh) | AL3: elec_demand ($/MWh) | AM3: h2_balance ($/MWh) | AN3: h2_demand ($/MWh) | AO3: gasoline_balance ($/MWh) | AP3: gasoline_demand ($/MWh) | AQ3: diesel_balance ($/MWh) | AR3: diesel_demand ($/MWh) | AS3: jetfuel_balance ($/MWh) | AT3: jetfuel_demand ($/MWh) | AU3: ng_balance ($/MWh) | AV3: ng_demand ($/MWh) | AW3: ethylene_balance ($/t) | AX3: ethylene_demand ($/t) | AZ3: id_LC | BA3: commodity_LC | BB3: LCOE ($/t-ethylene) | BC3: LCOE ($/t-ethylene) | BD3: Diff. Between Methods | BE3: LCOE ($/t-ethylene) | BF3: LCOE ($/t-ethylene) | BG3: Diff. Between Methods | BH3: h2_consumption | BI3: elec_consumption | BJ3: elec_consumption - ethanol | BK3: elec_production - ethanol | BL3: biomass_consumption - ethanol | BM3: natgas_consumption | BN3: natgas_consumption - ethanol | BO3: investment_cost | BP3: investment_cost - ethanol | BQ3: fixed_om_cost | BR3: fixed_om_cost - ethanol | BS3: variable_om_cost | BT3: variable_om_cost - ethanol | BU3: CI | BV3: modified capture cost | BW3: modified emissions cost | BX3: CI | BY3: modified capture cost | BZ3: modified emissions cost | CA3: CI | CB3: modified capture cost | CC3: modified emissions cost | CD3: CI | CE3: modified capture cost | CF3: modified emissions cost | CH3: id_LC_ethanol | CI3: elec_production | CJ3: elec_consumption | CK3: biomass_consumption | CL3: natgas_consumption | CM3: capture_rate | CN3: emission_rate | CO3: investment_cost | CP3: fixed_om_cost | CQ3: variable_om_cost | CS3: Ethylene (t-CO2/t-ethylene) | CT3: Biomass CO2 content (t-CO2/t-bio) | CU3: NG (t-CO2/MWh-NG) | CV3: Ethanol (t-CO2/MWh-ethanol) | CX3: Biomass (t-CO2/t-ethylene) | CY3: NG (t-CO2//t-ethylene) | CZ3: Ethanol (t-CO2//t-ethylene) | DA3: NG (t-CO2//t-ethylene) | DB3: Total input (t-CO2/t-ethylene) | DD3: Emissions (t-CO2/t-ethylene) | DE3: Captured (t-CO2/t-ethylene) | DF3: Ethylene (t-CO2/t-ethylene) | DG3: Emissions (t-CO2/t-ethylene) | DH3: Total Output (t-CO2/t-ethylene) | DJ3: CARBON INPUT - OUTPUT | DL3: ethanol_production_asset | DM3: id_ethanol_prod_ref | DN3: commodity_ethanol_prod_ref | DO3: elec_production (MWh/t-bio) | DP3: elec_consumption (MWh/t-bio) | DQ3: ethanol_production (MWh-ethanol/t-bio) | DR3: natgas_consumption (MWh/t-bio) | DS3: co2_biomass_content (t-CO2/t-bio) | DT3: capture_rate (t-CO2/t-bio) | DU3: emission_rate (t-CO2/t-bio) | DV3: investment_cost ($/yr per t-bio/hr) | DW3: fixed_om_cost ($/yr per t-bio/hr) | DX3: variable_om_cost ($/t-bio)
B4: SE_Ethanol_Dehydration_NGfuel | C4: Ethanol | D4: 1 | E4: =Q4 -> SE_DryMill_Existing_Non_CCS | F4: 0 | G4: 0.016231455 | H4: 0.070449025 | I4: 0.11456845 | J4: 0 | K4: 0.42269137 | L4: =(DA4+(CZ4-DF4))*H4 -> 1.6218958 | M4: 6577.9713 | N4: 6324.1329 | O4: 0.11130946 | Q4: {=_xlfn.XLOOKUP(D4, DL:DL, DM:DX)} -> SE_DryMill_Existing_Non_CCS | R4: Biomass_Corn | S4: 0 | T4: 0.06 | U4: 3.26 | V4: 0.75 | W4: 1.65 | X4: 0 | Y4: 1.034529 | Z4: 0 | AA4: 154043.63 | AB4: 79.65 | AD4: 122.13541 | AE4: -10.071578 | AF4: 73.297528 | AG4: 77.15826 | AH4: 59.694024 | AI4: 155 | AL4: 26.556269 | AM4: 8.627892 | AO4: -96.133976 | AP4: -96.133976 | AU4: 4.754684 | AV4: -0.136283 | AW4: 576.81127 | AX4: 576.81127 | AZ4: =B4 -> SE_Ethanol_Dehydration_NGfuel | BA4: =C4 -> Ethanol | BB4: =SUM(BH4:BT4)+BV4+BW4 -> 784.40643 | BC4: =SUM(BH4:BT4)+BY4+BZ4 -> 784.40643 | BD4: =BB4-BC4 -> 0 | BE4: =SUM(BH4:BT4)+CB4+CC4 -> 1167.9116 | BF4: =SUM(BH4:BT4)+CE4+CF4 -> 1167.9116 | BG4: =BE4-BF4 -> 0 | BH4: =F4/H4*AM4 -> 0 | BI4: =G4/H4*AL4 -> 6.1185644 | BJ4: =CJ4 -> 6.9378631 | BK4: =CI4 -> 0 | BL4: =CK4 -> 674.89951 | BM4: =I4/H4*AU4 -> 7.7323536 | BN4: =CL4 -> 15.527099 | BO4: =M4/H4/(0.9*8760) -> 11.843236 | BP4: =CO4 -> 0 | BQ4: =N4/H4/(0.9*8760) -> 11.386215 | BR4: =CP4 -> 85.075506 | BS4: =O4/H4 -> 1.58 | BT4: =CQ4 -> 346.81126 | BU4: =DB4-DH4-DF4 -> -3.14 | BV4: =(AD4+AE4)*-1*DE4 -> 0 | BW4: =BU4*AD4 -> -383.50518 | BX4: =DB4-DH4-DE4-DF4 -> -3.14 | BY4: =DE4*AE4*-1 -> 0 | BZ4: =BX4*AD4 -> -383.50518 | CA4: =DB4-DH4 -> 0 | CB4: =(AD4+AE4)*-1*DE4 -> 0 | CC4: =CA4*AD4 -> 0 | CD4: =DB4-DH4-DE4 -> 3.5527137e-15 | CE4: =DE4*AE4*-1 -> 0 | CF4: =CD4*AD4 -> 4.3391214e-13 | CH4: =Q4 -> SE_DryMill_Existing_Non_CCS | CI4: =S4/U4/H4*AL4*-1 -> 0 | CJ4: =T4/U4/H4*AL4 -> 6.9378631 | CK4: {=_xlfn.IFS(R4="Biomass_Corn", 1/U4/H4*AI4, R4="Biomass_Agri", 1/U4/H4*AH4, R4="Biomass_Wood", 1/U4/H4*AG4, R4="Biomass_Herb", 1/U4/H4*AF4)} -> 674.89951 | CL4: =V4/U4/H4*AU4 -> 15.527099 | CO4: =Z4/U4/H4/(0.9*8760) -> 0 | CP4: =AA4/U4/H4/(0.9*8760) -> 85.075506 | CQ4: =AB4/U4/H4 -> 346.81126 | CS4: 3.14 | CT4: =W4 -> 1.65 | CU4: 0.18104824 | CV4: =(CX4+CY4-DD4-DE4)*H4 -> 0.26284316 | CX4: =CT4/U4/H4 -> 7.1844141 | CY4: =IF(V4=0, 0, CU4/V4/U4/H4) -> 1.0510913 | CZ4: =CV4/H4 -> 3.7309694 | DA4: =IF(I4=0, 0, CU4/I4/H4) -> 22.431291 | DB4: =CX4+CY4+DA4 -> 30.666797 | DD4: =Y4/U4/H4 -> 4.504536 | DE4: =X4/U4/H4 -> 0 | DF4: =CS4 -> 3.14 | DG4: =L4/H4 -> 23.022261 | DH4: =SUM(DD4:DG4) -> 30.666797 | DJ4: =DB4-DH4 -> 0 | DL4: 1 | DM4: SE_DryMill_Existing_Non_CCS | DN4: Biomass_Corn | DO4: 0 | DP4: 0.06 | DQ4: 3.26 | DR4: 0.75 | DS4: 1.65 | DT4: 0 | DU4: 1.034529 | DV4: 0 | DW4: 154043.63 | DX4: 79.65
B5: SE_Ethanol_Dehydration_H2fuel | C5: Ethanol | D5: 1 | E5: =Q5 -> SE_DryMill_Existing_Non_CCS | F5: 0.11233878 | G5: 0.016231455 | H5: 0.070449025 | I5: 0 | J5: 0 | K5: 0.12825982 | L5: =(DA5+(CZ5-DF5))*H5 -> 0.041633218 | M5: 6577.9713 | N5: 6324.1329 | O5: 0.11130946 | Q5: {=_xlfn.XLOOKUP(D5, DL:DL, DM:DX)} -> SE_DryMill_Existing_Non_CCS | R5: Biomass_Corn | S5: 0 | T5: 0.06 | U5: 3.26 | V5: 0.75 | W5: 1.65 | X5: 0 | Y5: 1.034529 | Z5: 0 | AA5: 154043.63 | AB5: 79.65 | AD5: 122.13541 | AE5: -10.071578 | AF5: 73.297528 | AG5: 77.15826 | AH5: 59.694024 | AI5: 155 | AL5: 26.556269 | AM5: 8.627892 | AO5: -96.133976 | AP5: -96.133976 | AU5: 4.754684 | AV5: -0.136283 | AW5: 576.81127 | AX5: 576.81127 | AZ5: =B5 -> SE_Ethanol_Dehydration_H2fuel | BA5: =C5 -> Ethanol | BB5: =SUM(BH5:BT5)+BV5+BW5 -> 790.4322 | BC5: =SUM(BH5:BT5)+BY5+BZ5 -> 790.4322 | BD5: =BB5-BC5 -> 0 | BE5: =SUM(BH5:BT5)+CB5+CC5 -> 1173.9374 | BF5: =SUM(BH5:BT5)+CE5+CF5 -> 1173.9374 | BG5: =BE5-BF5 -> 0 | BH5: =F5/H5*AM5 -> 13.758131 | BI5: =G5/H5*AL5 -> 6.1185644 | BJ5: =CJ5 -> 6.9378631 | BK5: =CI5 -> 0 | BL5: =CK5 -> 674.89951 | BM5: =I5/H5*AU5 -> 0 | BN5: =CL5 -> 15.527099 | BO5: =M5/H5/(0.9*8760) -> 11.843236 | BP5: =CO5 -> 0 | BQ5: =N5/H5/(0.9*8760) -> 11.386215 | BR5: =CP5 -> 85.075506 | BS5: =O5/H5 -> 1.58 | BT5: =CQ5 -> 346.81126 | BU5: =DB5-DH5-DF5 -> -3.14 | BV5: =(AD5+AE5)*-1*DE5 -> 0 | BW5: =BU5*AD5 -> -383.50518 | BX5: =DB5-DH5-DE5-DF5 -> -3.14 | BY5: =DE5*AE5*-1 -> 0 | BZ5: =BX5*AD5 -> -383.50518 | CA5: =DB5-DH5 -> 0 | CB5: =(AD5+AE5)*-1*DE5 -> 0 | CC5: =CA5*AD5 -> 0 | CD5: =DB5-DH5-DE5 -> 0 | CE5: =DE5*AE5*-1 -> 0 | CF5: =CD5*AD5 -> 0 | CH5: =Q5 -> SE_DryMill_Existing_Non_CCS | CI5: =S5/U5/H5*AL5*-1 -> 0 | CJ5: =T5/U5/H5*AL5 -> 6.9378631 | CK5: {=_xlfn.IFS(R5="Biomass_Corn", 1/U5/H5*AI5, R5="Biomass_Agri", 1/U5/H5*AH5, R5="Biomass_Wood", 1/U5/H5*AG5, R5="Biomass_Herb", 1/U5/H5*AF5)} -> 674.89951 | CL5: =V5/U5/H5*AU5 -> 15.527099 | CO5: =Z5/U5/H5/(0.9*8760) -> 0 | CP5: =AA5/U5/H5/(0.9*8760) -> 85.075506 | CQ5: =AB5/U5/H5 -> 346.81126 | CS5: 3.14 | CT5: =W5 -> 1.65 | CU5: 0.18104824 | CV5: =(CX5+CY5-DD5-DE5)*H5 -> 0.26284316 | CX5: =CT5/U5/H5 -> 7.1844141 | CY5: =IF(V5=0, 0, CU5/V5/U5/H5) -> 1.0510913 | CZ5: =CV5/H5 -> 3.7309694 | DA5: =IF(I5=0, 0, CU5/I5/H5) -> 0 | DB5: =CX5+CY5+DA5 -> 8.2355054 | DD5: =Y5/U5/H5 -> 4.504536 | DE5: =X5/U5/H5 -> 0 | DF5: =CS5 -> 3.14 | DG5: =L5/H5 -> 0.59096941 | DH5: =SUM(DD5:DG5) -> 8.2355054 | DJ5: =DB5-DH5 -> 0 | DL5: 2 | DM5: SE_Biochemical_Non_CCS | DN5: Biomass_Agri | DO5: 0.1227 | DP5: 0 | DQ5: 1.5509 | DR5: 0 | DS5: 1.32 | DT5: 0 | DU5: 0.96259975 | DV5: 656536.27 | DW5: 194987.35 | DX5: 55.68
B6: CA_Ethanol_Dehydration_NGfuel | C6: Ethanol | D6: 1 | E6: =Q6 -> SE_DryMill_Existing_Non_CCS | F6: 0 | G6: 0.016231455 | H6: 0.070449025 | I6: 0.11456845 | J6: 0 | K6: 0.42269137 | L6: =(DA6+(CZ6-DF6))*H6 -> 1.6218958 | M6: 6577.9713 | N6: 6324.1329 | O6: 0.11130946 | Q6: {=_xlfn.XLOOKUP(D6, DL:DL, DM:DX)} -> SE_DryMill_Existing_Non_CCS | R6: Biomass_Corn | S6: 0 | T6: 0.06 | U6: 3.26 | V6: 0.75 | W6: 1.65 | X6: 0 | Y6: 1.034529 | Z6: 0 | AA6: 154043.63 | AB6: 79.65 | AD6: 122.13541 | AE6: -6.496536 | AF6: 117.62504 | AG6: 88.648826 | AH6: 72.811197 | AI6: 155 | AL6: 25.313633 | AM6: 8.809073 | AO6: 0 | AP6: 0 | AU6: 11.573017 | AV6: 0 | AW6: 576.81127 | AX6: 0 | AZ6: =B6 -> CA_Ethanol_Dehydration_NGfuel | BA6: =C6 -> Ethanol | BB6: =SUM(BH6:BT6)+BV6+BW6 -> 817.15011 | BC6: =SUM(BH6:BT6)+BY6+BZ6 -> 817.15011 | BD6: =BB6-BC6 -> 0 | BE6: =SUM(BH6:BT6)+CB6+CC6 -> 1200.6553 | BF6: =SUM(BH6:BT6)+CE6+CF6 -> 1200.6553 | BG6: =BE6-BF6 -> 0 | BH6: =F6/H6*AM6 -> 0 | BI6: =G6/H6*AL6 -> 5.832261 | BJ6: =CJ6 -> 6.6132226 | BK6: =CI6 -> 0 | BL6: =CK6 -> 674.89951 | BM6: =I6/H6*AU6 -> 18.820738 | BN6: =CL6 -> 37.793339 | BO6: =M6/H6/(0.9*8760) -> 11.843236 | BP6: =CO6 -> 0 | BQ6: =N6/H6/(0.9*8760) -> 11.386215 | BR6: =CP6 -> 85.075506 | BS6: =O6/H6 -> 1.58 | BT6: =CQ6 -> 346.81126 | BU6: =DB6-DH6-DF6 -> -3.14 | BV6: =(AD6+AE6)*-1*DE6 -> 0 | BW6: =BU6*AD6 -> -383.50518 | BX6: =DB6-DH6-DE6-DF6 -> -3.14 | BY6: =DE6*AE6*-1 -> 0 | BZ6: =BX6*AD6 -> -383.50518 | CA6: =DB6-DH6 -> 0 | CB6: =(AD6+AE6)*-1*DE6 -> 0 | CC6: =CA6*AD6 -> 0 | CD6: =DB6-DH6-DE6 -> 3.5527137e-15 | CE6: =DE6*AE6*-1 -> 0 | CF6: =CD6*AD6 -> 4.3391214e-13 | CH6: =Q6 -> SE_DryMill_Existing_Non_CCS | CI6: =S6/U6/H6*AL6*-1 -> 0 | CJ6: =T6/U6/H6*AL6 -> 6.6132226 | CK6: {=_xlfn.IFS(R6="Biomass_Corn", 1/U6/H6*AI6, R6="Biomass_Agri", 1/U6/H6*AH6, R6="Biomass_Wood", 1/U6/H6*AG6, R6="Biomass_Herb", 1/U6/H6*AF6)} -> 674.89951 | CL6: =V6/U6/H6*AU6 -> 37.793339 | CO6: =Z6/U6/H6/(0.9*8760) -> 0 | CP6: =AA6/U6/H6/(0.9*8760) -> 85.075506 | CQ6: =AB6/U6/H6 -> 346.81126 | CS6: 3.14 | CT6: =W6 -> 1.65 | CU6: 0.18104824 | CV6: =(CX6+CY6-DD6-DE6)*H6 -> 0.26284316 | CX6: =CT6/U6/H6 -> 7.1844141 | CY6: =IF(V6=0, 0, CU6/V6/U6/H6) -> 1.0510913 | CZ6: =CV6/H6 -> 3.7309694 | DA6: =IF(I6=0, 0, CU6/I6/H6) -> 22.431291 | DB6: =CX6+CY6+DA6 -> 30.666797 | DD6: =Y6/U6/H6 -> 4.504536 | DE6: =X6/U6/H6 -> 0 | DF6: =CS6 -> 3.14 | DG6: =L6/H6 -> 23.022261 | DH6: =SUM(DD6:DG6) -> 30.666797 | DJ6: =DB6-DH6 -> 0 | DL6: 3 | DM6: SE_Biochemical_CCS_20 | DN6: Biomass_Agri | DO6: 0.1227 | DP6: 0 | DQ6: 1.5509 | DR6: 0 | DS6: 1.32 | DT6: 0.19 | DU6: 0.77259975 | DV6: 658128.84 | DW6: 195838.97 | DX6: 55.71
B7: CA_Ethanol_Dehydration_H2fuel | C7: Ethanol | D7: 1 | E7: =Q7 -> SE_DryMill_Existing_Non_CCS | F7: 0.11233878 | G7: 0.016231455 | H7: 0.070449025 | I7: 0 | J7: 0 | K7: 0.12825982 | L7: =(DA7+(CZ7-DF7))*H7 -> 0.041633218 | M7: 6577.9713 | N7: 6324.1329 | O7: 0.11130946 | Q7: {=_xlfn.XLOOKUP(D7, DL:DL, DM:DX)} -> SE_DryMill_Existing_Non_CCS | R7: Biomass_Corn | S7: 0 | T7: 0.06 | U7: 3.26 | V7: 0.75 | W7: 1.65 | X7: 0 | Y7: 1.034529 | Z7: 0 | AA7: 154043.63 | AB7: 79.65 | AD7: 122.13541 | AE7: -6.496536 | AF7: 117.62504 | AG7: 88.648826 | AH7: 72.811197 | AI7: 155 | AL7: 25.313633 | AM7: 8.809073 | AO7: 0 | AP7: 0 | AU7: 11.573017 | AV7: 0 | AW7: 576.81127 | AX7: 0 | AZ7: =B7 -> CA_Ethanol_Dehydration_H2fuel | BA7: =C7 -> Ethanol | BB7: =SUM(BH7:BT7)+BV7+BW7 -> 812.37641 | BC7: =SUM(BH7:BT7)+BY7+BZ7 -> 812.37641 | BD7: =BB7-BC7 -> 0 | BE7: =SUM(BH7:BT7)+CB7+CC7 -> 1195.8816 | BF7: =SUM(BH7:BT7)+CE7+CF7 -> 1195.8816 | BG7: =BE7-BF7 -> 0 | BH7: =F7/H7*AM7 -> 14.047044 | BI7: =G7/H7*AL7 -> 5.832261 | BJ7: =CJ7 -> 6.6132226 | BK7: =CI7 -> 0 | BL7: =CK7 -> 674.89951 | BM7: =I7/H7*AU7 -> 0 | BN7: =CL7 -> 37.793339 | BO7: =M7/H7/(0.9*8760) -> 11.843236 | BP7: =CO7 -> 0 | BQ7: =N7/H7/(0.9*8760) -> 11.386215 | BR7: =CP7 -> 85.075506 | BS7: =O7/H7 -> 1.58 | BT7: =CQ7 -> 346.81126 | BU7: =DB7-DH7-DF7 -> -3.14 | BV7: =(AD7+AE7)*-1*DE7 -> 0 | BW7: =BU7*AD7 -> -383.50518 | BX7: =DB7-DH7-DE7-DF7 -> -3.14 | BY7: =DE7*AE7*-1 -> 0 | BZ7: =BX7*AD7 -> -383.50518 | CA7: =DB7-DH7 -> 0 | CB7: =(AD7+AE7)*-1*DE7 -> 0 | CC7: =CA7*AD7 -> 0 | CD7: =DB7-DH7-DE7 -> 0 | CE7: =DE7*AE7*-1 -> 0 | CF7: =CD7*AD7 -> 0 | CH7: =Q7 -> SE_DryMill_Existing_Non_CCS | CI7: =S7/U7/H7*AL7*-1 -> 0 | CJ7: =T7/U7/H7*AL7 -> 6.6132226 | CK7: {=_xlfn.IFS(R7="Biomass_Corn", 1/U7/H7*AI7, R7="Biomass_Agri", 1/U7/H7*AH7, R7="Biomass_Wood", 1/U7/H7*AG7, R7="Biomass_Herb", 1/U7/H7*AF7)} -> 674.89951 | CL7: =V7/U7/H7*AU7 -> 37.793339 | CO7: =Z7/U7/H7/(0.9*8760) -> 0 | CP7: =AA7/U7/H7/(0.9*8760) -> 85.075506 | CQ7: =AB7/U7/H7 -> 346.81126 | CS7: 3.14 | CT7: =W7 -> 1.65 | CU7: 0.18104824 | CV7: =(CX7+CY7-DD7-DE7)*H7 -> 0.26284316 | CX7: =CT7/U7/H7 -> 7.1844141 | CY7: =IF(V7=0, 0, CU7/V7/U7/H7) -> 1.0510913 | CZ7: =CV7/H7 -> 3.7309694 | DA7: =IF(I7=0, 0, CU7/I7/H7) -> 0 | DB7: =CX7+CY7+DA7 -> 8.2355054 | DD7: =Y7/U7/H7 -> 4.504536 | DE7: =X7/U7/H7 -> 0 | DF7: =CS7 -> 3.14 | DG7: =L7/H7 -> 0.59096941 | DH7: =SUM(DD7:DG7) -> 8.2355054 | DJ7: =DB7-DH7 -> 0 | DL7: 4 | DM7: SE_Biochemical_CCS_86 | DN7: Biomass_Agri | DO7: 0.1227 | DP7: 0.26 | DQ7: 1.5509 | DR7: 0 | DS7: 1.32 | DT7: 0.83 | DU7: 0.13259975 | DV7: 727064.6 | DW7: 233553.61 | DX7: 56.9
B8: SE_Ethanol_Dehydration_NGfuel_ethanol_biochemical | C8: Ethanol | D8: 2 | E8: =Q8 -> SE_Biochemical_Non_CCS | F8: 0 | G8: 0.016231455 | H8: 0.070449025 | I8: 0.11456845 | J8: 0 | K8: 0.42269137 | L8: =(DA8+(CZ8-DF8))*H8 -> 1.5894997 | M8: 6577.9713 | N8: 6324.1329 | O8: 0.11130946 | Q8: {=_xlfn.XLOOKUP(D8, DL:DL, DM:DX)} -> SE_Biochemical_Non_CCS | R8: Biomass_Agri | S8: 0.1227 | T8: 0 | U8: 1.5509 | V8: 0 | W8: 1.32 | X8: 0 | Y8: 0.96259975 | Z8: 656536.27 | AA8: 194987.35 | AB8: 55.68 | AD8: 122.13541 | AE8: -10.071578 | AF8: 73.297528 | AG8: 77.15826 | AH8: 59.694024 | AI8: 155 | AL8: 26.556269 | AM8: 8.627892 | AO8: -96.133976 | AP8: -96.133976 | AU8: 4.754684 | AV8: -0.136283 | AW8: 576.81127 | AX8: 576.81127 | AZ8: =B8 -> SE_Ethanol_Dehydration_NGfuel_ethanol_biochemical | BA8: =C8 -> Ethanol | BB8: =SUM(BH8:BT8)+BV8+BW8 -> 1669.8297 | BC8: =SUM(BH8:BT8)+BY8+BZ8 -> 1669.8297 | BD8: =BB8-BC8 -> 0 | BE8: =SUM(BH8:BT8)+CB8+CC8 -> 2053.3349 | BF8: =SUM(BH8:BT8)+CE8+CF8 -> 2053.3349 | BG8: =BE8-BF8 -> 0 | BH8: =F8/H8*AM8 -> 0 | BI8: =G8/H8*AL8 -> 6.1185644 | BJ8: =CJ8 -> 0 | BK8: =CI8 -> -29.823104 | BL8: =CK8 -> 546.35142 | BM8: =I8/H8*AU8 -> 7.7323536 | BN8: =CL8 -> 0 | BO8: =M8/H8/(0.9*8760) -> 11.843236 | BP8: =CO8 -> 762.17259 | BQ8: =N8/H8/(0.9*8760) -> 11.386215 | BR8: =CP8 -> 226.36071 | BS8: =O8/H8 -> 1.58 | BT8: =CQ8 -> 509.61294 | BU8: =DB8-DH8-DF8 -> -3.14 | BV8: =(AD8+AE8)*-1*DE8 -> 0 | BW8: =BU8*AD8 -> -383.50518 | BX8: =DB8-DH8-DE8-DF8 -> -3.14 | BY8: =DE8*AE8*-1 -> 0 | BZ8: =BX8*AD8 -> -383.50518 | CA8: =DB8-DH8 -> 0 | CB8: =(AD8+AE8)*-1*DE8 -> 0 | CC8: =CA8*AD8 -> 0 | CD8: =DB8-DH8-DE8 -> 0 | CE8: =DE8*AE8*-1 -> 0 | CF8: =CD8*AD8 -> 0 | CH8: =Q8 -> SE_Biochemical_Non_CCS | CI8: =S8/U8/H8*AL8*-1 -> -29.823104 | CJ8: =T8/U8/H8*AL8 -> 0 | CK8: {=_xlfn.IFS(R8="Biomass_Corn", 1/U8/H8*AI8, R8="Biomass_Agri", 1/U8/H8*AH8, R8="Biomass_Wood", 1/U8/H8*AG8, R8="Biomass_Herb", 1/U8/H8*AF8)} -> 546.35142 | CL8: =V8/U8/H8*AU8 -> 0 | CO8: =Z8/U8/H8/(0.9*8760) -> 762.17259 | CP8: =AA8/U8/H8/(0.9*8760) -> 226.36071 | CQ8: =AB8/U8/H8 -> 509.61294 | CS8: 3.14 | CT8: =W8 -> 1.32 | CU8: 0.18104824 | CV8: =(CX8+CY8-DD8-DE8)*H8 -> 0.230447 | CX8: =CT8/U8/H8 -> 12.081341 | CY8: =IF(V8=0, 0, CU8/V8/U8/H8) -> 0 | CZ8: =CV8/H8 -> 3.271117 | DA8: =IF(I8=0, 0, CU8/I8/H8) -> 22.431291 | DB8: =CX8+CY8+DA8 -> 34.512632 | DD8: =Y8/U8/H8 -> 8.8102242 | DE8: =X8/U8/H8 -> 0 | DF8: =CS8 -> 3.14 | DG8: =L8/H8 -> 22.562408 | DH8: =SUM(DD8:DG8) -> 34.512632 | DJ8: =DB8-DH8 -> 0 | DL8: 5 | DM8: SE_DryMill_Retrofit_CCS_90 | DN8: Biomass_Corn | DO8: 0 | DP8: 0.06 | DQ8: 3.26 | DR8: 0.75 | DS8: 1.65 | DT8: 0 | DU8: 1.034529 | DV8: 10000 | DW8: 154043.63 | DX8: 79.65
B9: SE_Ethanol_Dehydration_H2fuel_ethanol_biochemical | C9: Ethanol | D9: 2 | E9: =Q9 -> SE_Biochemical_Non_CCS | F9: 0.11233878 | G9: 0.016231455 | H9: 0.070449025 | I9: 0 | J9: 0 | K9: 0.12825982 | L9: =(DA9+(CZ9-DF9))*H9 -> 0.0092370618 | M9: 6577.9713 | N9: 6324.1329 | O9: 0.11130946 | Q9: {=_xlfn.XLOOKUP(D9, DL:DL, DM:DX)} -> SE_Biochemical_Non_CCS | R9: Biomass_Agri | S9: 0.1227 | T9: 0 | U9: 1.5509 | V9: 0 | W9: 1.32 | X9: 0 | Y9: 0.96259975 | Z9: 656536.27 | AA9: 194987.35 | AB9: 55.68 | AD9: 122.13541 | AE9: -10.071578 | AF9: 73.297528 | AG9: 77.15826 | AH9: 59.694024 | AI9: 155 | AL9: 26.556269 | AM9: 8.627892 | AO9: -96.133976 | AP9: -96.133976 | AU9: 4.754684 | AV9: -0.136283 | AW9: 576.81127 | AX9: 576.81127 | AZ9: =B9 -> SE_Ethanol_Dehydration_H2fuel_ethanol_biochemical | BA9: =C9 -> Ethanol | BB9: =SUM(BH9:BT9)+BV9+BW9 -> 1675.8555 | BC9: =SUM(BH9:BT9)+BY9+BZ9 -> 1675.8555 | BD9: =BB9-BC9 -> 0 | BE9: =SUM(BH9:BT9)+CB9+CC9 -> 2059.3607 | BF9: =SUM(BH9:BT9)+CE9+CF9 -> 2059.3607 | BG9: =BE9-BF9 -> 0 | BH9: =F9/H9*AM9 -> 13.758131 | BI9: =G9/H9*AL9 -> 6.1185644 | BJ9: =CJ9 -> 0 | BK9: =CI9 -> -29.823104 | BL9: =CK9 -> 546.35142 | BM9: =I9/H9*AU9 -> 0 | BN9: =CL9 -> 0 | BO9: =M9/H9/(0.9*8760) -> 11.843236 | BP9: =CO9 -> 762.17259 | BQ9: =N9/H9/(0.9*8760) -> 11.386215 | BR9: =CP9 -> 226.36071 | BS9: =O9/H9 -> 1.58 | BT9: =CQ9 -> 509.61294 | BU9: =DB9-DH9-DF9 -> -3.14 | BV9: =(AD9+AE9)*-1*DE9 -> 0 | BW9: =BU9*AD9 -> -383.50518 | BX9: =DB9-DH9-DE9-DF9 -> -3.14 | BY9: =DE9*AE9*-1 -> 0 | BZ9: =BX9*AD9 -> -383.50518 | CA9: =DB9-DH9 -> 0 | CB9: =(AD9+AE9)*-1*DE9 -> 0 | CC9: =CA9*AD9 -> 0 | CD9: =DB9-DH9-DE9 -> 0 | CE9: =DE9*AE9*-1 -> 0 | CF9: =CD9*AD9 -> 0 | CH9: =Q9 -> SE_Biochemical_Non_CCS | CI9: =S9/U9/H9*AL9*-1 -> -29.823104 | CJ9: =T9/U9/H9*AL9 -> 0 | CK9: {=_xlfn.IFS(R9="Biomass_Corn", 1/U9/H9*AI9, R9="Biomass_Agri", 1/U9/H9*AH9, R9="Biomass_Wood", 1/U9/H9*AG9, R9="Biomass_Herb", 1/U9/H9*AF9)} -> 546.35142 | CL9: =V9/U9/H9*AU9 -> 0 | CO9: =Z9/U9/H9/(0.9*8760) -> 762.17259 | CP9: =AA9/U9/H9/(0.9*8760) -> 226.36071 | CQ9: =AB9/U9/H9 -> 509.61294 | CS9: 3.14 | CT9: =W9 -> 1.32 | CU9: 0.18104824 | CV9: =(CX9+CY9-DD9-DE9)*H9 -> 0.230447 | CX9: =CT9/U9/H9 -> 12.081341 | CY9: =IF(V9=0, 0, CU9/V9/U9/H9) -> 0 | CZ9: =CV9/H9 -> 3.271117 | DA9: =IF(I9=0, 0, CU9/I9/H9) -> 0 | DB9: =CX9+CY9+DA9 -> 12.081341 | DD9: =Y9/U9/H9 -> 8.8102242 | DE9: =X9/U9/H9 -> 0 | DF9: =CS9 -> 3.14 | DG9: =L9/H9 -> 0.13111696 | DH9: =SUM(DD9:DG9) -> 12.081341 | DJ9: =DB9-DH9 -> 0
B10: CA_Ethanol_Dehydration_NGfuel_ethanol_biochemical | C10: Ethanol | D10: 2 | E10: =Q10 -> SE_Biochemical_Non_CCS | F10: 0 | G10: 0.016231455 | H10: 0.070449025 | I10: 0.11456845 | J10: 0 | K10: 0.42269137 | L10: =(DA10+(CZ10-DF10))*H10 -> 1.5894997 | M10: 6577.9713 | N10: 6324.1329 | O10: 0.11130946 | Q10: {=_xlfn.XLOOKUP(D10, DL:DL, DM:DX)} -> SE_Biochemical_Non_CCS | R10: Biomass_Agri | S10: 0.1227 | T10: 0 | U10: 1.5509 | V10: 0 | W10: 1.32 | X10: 0 | Y10: 0.96259975 | Z10: 656536.27 | AA10: 194987.35 | AB10: 55.68 | AD10: 122.13541 | AE10: -6.496536 | AF10: 117.62504 | AG10: 88.648826 | AH10: 72.811197 | AI10: 155 | AL10: 25.313633 | AM10: 8.809073 | AO10: 0 | AP10: 0 | AU10: 11.573017 | AV10: 0 | AW10: 576.81127 | AX10: 0 | AZ10: =B10 -> CA_Ethanol_Dehydration_NGfuel_ethanol_biochemical | BA10: =C10 -> Ethanol | BB10: =SUM(BH10:BT10)+BV10+BW10 -> 1802.0826 | BC10: =SUM(BH10:BT10)+BY10+BZ10 -> 1802.0826 | BD10: =BB10-BC10 -> 0 | BE10: =SUM(BH10:BT10)+CB10+CC10 -> 2185.5878 | BF10: =SUM(BH10:BT10)+CE10+CF10 -> 2185.5878 | BG10: =BE10-BF10 -> 0 | BH10: =F10/H10*AM10 -> 0 | BI10: =G10/H10*AL10 -> 5.832261 | BJ10: =CJ10 -> 0 | BK10: =CI10 -> -28.427604 | BL10: =CK10 -> 666.40675 | BM10: =I10/H10*AU10 -> 18.820738 | BN10: =CL10 -> 0 | BO10: =M10/H10/(0.9*8760) -> 11.843236 | BP10: =CO10 -> 762.17259 | BQ10: =N10/H10/(0.9*8760) -> 11.386215 | BR10: =CP10 -> 226.36071 | BS10: =O10/H10 -> 1.58 | BT10: =CQ10 -> 509.61294 | BU10: =DB10-DH10-DF10 -> -3.14 | BV10: =(AD10+AE10)*-1*DE10 -> 0 | BW10: =BU10*AD10 -> -383.50518 | BX10: =DB10-DH10-DE10-DF10 -> -3.14 | BY10: =DE10*AE10*-1 -> 0 | BZ10: =BX10*AD10 -> -383.50518 | CA10: =DB10-DH10 -> 0 | CB10: =(AD10+AE10)*-1*DE10 -> 0 | CC10: =CA10*AD10 -> 0 | CD10: =DB10-DH10-DE10 -> 0 | CE10: =DE10*AE10*-1 -> 0 | CF10: =CD10*AD10 -> 0 | CH10: =Q10 -> SE_Biochemical_Non_CCS | CI10: =S10/U10/H10*AL10*-1 -> -28.427604 | CJ10: =T10/U10/H10*AL10 -> 0 | CK10: {=_xlfn.IFS(R10="Biomass_Corn", 1/U10/H10*AI10, R10="Biomass_Agri", 1/U10/H10*AH10, R10="Biomass_Wood", 1/U10/H10*AG10, R10="Biomass_Herb", 1/U10/H10*AF10)} -> 666.40675 | CL10: =V10/U10/H10*AU10 -> 0 | CO10: =Z10/U10/H10/(0.9*8760) -> 762.17259 | CP10: =AA10/U10/H10/(0.9*8760) -> 226.36071 | CQ10: =AB10/U10/H10 -> 509.61294 | CS10: 3.14 | CT10: =W10 -> 1.32 | CU10: 0.18104824 | CV10: =(CX10+CY10-DD10-DE10)*H10 -> 0.230447 | CX10: =CT10/U10/H10 -> 12.081341 | CY10: =IF(V10=0, 0, CU10/V10/U10/H10) -> 0 | CZ10: =CV10/H10 -> 3.271117 | DA10: =IF(I10=0, 0, CU10/I10/H10) -> 22.431291 | DB10: =CX10+CY10+DA10 -> 34.512632 | DD10: =Y10/U10/H10 -> 8.8102242 | DE10: =X10/U10/H10 -> 0 | DF10: =CS10 -> 3.14 | DG10: =L10/H10 -> 22.562408 | DH10: =SUM(DD10:DG10) -> 34.512632 | DJ10: =DB10-DH10 -> 0
B11: CA_Ethanol_Dehydration_H2fuel_ethanol_biochemical | C11: Ethanol | D11: 2 | E11: =Q11 -> SE_Biochemical_Non_CCS | F11: 0.11233878 | G11: 0.016231455 | H11: 0.070449025 | I11: 0 | J11: 0 | K11: 0.12825982 | L11: =(DA11+(CZ11-DF11))*H11 -> 0.0092370618 | M11: 6577.9713 | N11: 6324.1329 | O11: 0.11130946 | Q11: {=_xlfn.XLOOKUP(D11, DL:DL, DM:DX)} -> SE_Biochemical_Non_CCS | R11: Biomass_Agri | S11: 0.1227 | T11: 0 | U11: 1.5509 | V11: 0 | W11: 1.32 | X11: 0 | Y11: 0.96259975 | Z11: 656536.27 | AA11: 194987.35 | AB11: 55.68 | AD11: 122.13541 | AE11: -6.496536 | AF11: 117.62504 | AG11: 88.648826 | AH11: 72.811197 | AI11: 155 | AL11: 25.313633 | AM11: 8.809073 | AO11: 0 | AP11: 0 | AU11: 11.573017 | AV11: 0 | AW11: 576.81127 | AX11: 0 | AZ11: =B11 -> CA_Ethanol_Dehydration_H2fuel_ethanol_biochemical | BA11: =C11 -> Ethanol | BB11: =SUM(BH11:BT11)+BV11+BW11 -> 1797.309 | BC11: =SUM(BH11:BT11)+BY11+BZ11 -> 1797.309 | BD11: =BB11-BC11 -> 0 | BE11: =SUM(BH11:BT11)+CB11+CC11 -> 2180.8141 | BF11: =SUM(BH11:BT11)+CE11+CF11 -> 2180.8141 | BG11: =BE11-BF11 -> 0 | BH11: =F11/H11*AM11 -> 14.047044 | BI11: =G11/H11*AL11 -> 5.832261 | BJ11: =CJ11 -> 0 | BK11: =CI11 -> -28.427604 | BL11: =CK11 -> 666.40675 | BM11: =I11/H11*AU11 -> 0 | BN11: =CL11 -> 0 | BO11: =M11/H11/(0.9*8760) -> 11.843236 | BP11: =CO11 -> 762.17259 | BQ11: =N11/H11/(0.9*8760) -> 11.386215 | BR11: =CP11 -> 226.36071 | BS11: =O11/H11 -> 1.58 | BT11: =CQ11 -> 509.61294 | BU11: =DB11-DH11-DF11 -> -3.14 | BV11: =(AD11+AE11)*-1*DE11 -> 0 | BW11: =BU11*AD11 -> -383.50518 | BX11: =DB11-DH11-DE11-DF11 -> -3.14 | BY11: =DE11*AE11*-1 -> 0 | BZ11: =BX11*AD11 -> -383.50518 | CA11: =DB11-DH11 -> 0 | CB11: =(AD11+AE11)*-1*DE11 -> 0 | CC11: =CA11*AD11 -> 0 | CD11: =DB11-DH11-DE11 -> 0 | CE11: =DE11*AE11*-1 -> 0 | CF11: =CD11*AD11 -> 0 | CH11: =Q11 -> SE_Biochemical_Non_CCS | CI11: =S11/U11/H11*AL11*-1 -> -28.427604 | CJ11: =T11/U11/H11*AL11 -> 0 | CK11: {=_xlfn.IFS(R11="Biomass_Corn", 1/U11/H11*AI11, R11="Biomass_Agri", 1/U11/H11*AH11, R11="Biomass_Wood", 1/U11/H11*AG11, R11="Biomass_Herb", 1/U11/H11*AF11)} -> 666.40675 | CL11: =V11/U11/H11*AU11 -> 0 | CO11: =Z11/U11/H11/(0.9*8760) -> 762.17259 | CP11: =AA11/U11/H11/(0.9*8760) -> 226.36071 | CQ11: =AB11/U11/H11 -> 509.61294 | CS11: 3.14 | CT11: =W11 -> 1.32 | CU11: 0.18104824 | CV11: =(CX11+CY11-DD11-DE11)*H11 -> 0.230447 | CX11: =CT11/U11/H11 -> 12.081341 | CY11: =IF(V11=0, 0, CU11/V11/U11/H11) -> 0 | CZ11: =CV11/H11 -> 3.271117 | DA11: =IF(I11=0, 0, CU11/I11/H11) -> 0 | DB11: =CX11+CY11+DA11 -> 12.081341 | DD11: =Y11/U11/H11 -> 8.8102242 | DE11: =X11/U11/H11 -> 0 | DF11: =CS11 -> 3.14 | DG11: =L11/H11 -> 0.13111696 | DH11: =SUM(DD11:DG11) -> 12.081341 | DJ11: =DB11-DH11 -> 0

Sheet lc_summary
B2: Levelized cost for Bioethylene Production - $/GJ-ethylene - no chemicals CO2 sequestration | W2: Levelized cost for Bioethylene Production - $/GJ-ethylene - chemicals CO2 sequestration | AR2: Assumptions
B3: id_LC | C3: h2_consumption | D3: elec_consumption | E3: elec_consumption - ethanol | F3: elec_production - ethanol | G3: biomass_consumption - ethanol | H3: natgas_consumption | I3: natgas_consumption - ethanol | J3: investment_cost | K3: investment_cost - ethanol | L3: fixed_om_cost | M3: fixed_om_cost - ethanol | N3: variable_om_cost | O3: variable_om_cost - ethanol | P3: modified capture cost | Q3: modified emissions cost | R3: CI | S3: LCOE ($/t-ethylene) | T3: LCOE ($/GJ-ethylene) | U3: CHECK LCOE ($/t-ethylene) | W3: id_LC | X3: h2_consumption | Y3: elec_consumption | Z3: elec_consumption - ethanol | AA3: elec_production - ethanol | AB3: biomass_consumption - ethanol | AC3: natgas_consumption | AD3: natgas_consumption - ethanol | AE3: investment_cost | AF3: investment_cost - ethanol | AG3: fixed_om_cost | AH3: fixed_om_cost - ethanol | AI3: variable_om_cost | AJ3: variable_om_cost - ethanol | AK3: modified capture cost | AL3: modified emissions cost | AM3: CI | AN3: LCOE ($/t-ethylene) | AO3: LCOE ($/GJ-ethylene) | AP3: CHECK LCOE ($/t-ethylene) | AR3: Ethylene LHV | AS3: 45.6 | AT3: GJ/t-ethylene
B4: =lc_detailed!AZ4 -> SE_Ethanol_Dehydration_NGfuel | C4: =lc_detailed!BH4/$AS$3 -> 0 | D4: =lc_detailed!BI4/$AS$3 -> 0.13417904 | E4: =lc_detailed!BJ4/$AS$3 -> 0.15214612 | F4: =lc_detailed!BK4/$AS$3 -> 0 | G4: =lc_detailed!BL4/$AS$3 -> 14.800428 | H4: =lc_detailed!BM4/$AS$3 -> 0.16956916 | I4: =lc_detailed!BN4/$AS$3 -> 0.34050657 | J4: =lc_detailed!BO4/$AS$3 -> 0.25972008 | ... O4: =lc_detailed!BT4/$AS$3 -> 7.6055102 | P4: =lc_detailed!CB4/$AS$3 -> 0 | Q4: =lc_detailed!CC4/$AS$3 -> 0 | R4: =lc_detailed!CA4/$AS$3 -> 0 | S4: =lc_detailed!BE4 -> 1167.9116 | T4: =SUM(C4:Q4) -> 25.612097 | U4: =T4*$AS$3 -> 1167.9116 | W4: =lc_detailed!AZ4 -> SE_Ethanol_Dehydration_NGfuel | X4: =lc_detailed!BH4/$AS$3 -> 0 | Y4: =lc_detailed!BI4/$AS$3 -> 0.13417904 | Z4: =lc_detailed!BJ4/$AS$3 -> 0.15214612 | AA4: =lc_detailed!BK4/$AS$3 -> 0 | AB4: =lc_detailed!BL4/$AS$3 -> 14.800428 | AC4: =lc_detailed!BM4/$AS$3 -> 0.16956916 | AD4: =lc_detailed!BN4/$AS$3 -> 0.34050657 | AE4: =lc_detailed!BO4/$AS$3 -> 0.25972008 | ... AJ4: =lc_detailed!BT4/$AS$3 -> 7.6055102 | AK4: =lc_detailed!BV4/$AS$3 -> 0 | AL4: =lc_detailed!BW4/$AS$3 -> -8.4102014 | AM4: =lc_detailed!BU4/$AS$3 -> -0.068859649 | AN4: =lc_detailed!BB4 -> 784.40643 | AO4: =SUM(X4:AL4) -> 17.201895 | AP4: =AO4*$AS$3 -> 784.40643
B5: =lc_detailed!AZ5 -> SE_Ethanol_Dehydration_H2fuel | C5: =lc_detailed!BH5/$AS$3 -> 0.30171339 | D5: =lc_detailed!BI5/$AS$3 -> 0.13417904 | E5: =lc_detailed!BJ5/$AS$3 -> 0.15214612 | F5: =lc_detailed!BK5/$AS$3 -> 0 | G5: =lc_detailed!BL5/$AS$3 -> 14.800428 | H5: =lc_detailed!BM5/$AS$3 -> 0 | I5: =lc_detailed!BN5/$AS$3 -> 0.34050657 | J5: =lc_detailed!BO5/$AS$3 -> 0.25972008 | ... O5: =lc_detailed!BT5/$AS$3 -> 7.6055102 | P5: =lc_detailed!CB5/$AS$3 -> 0 | Q5: =lc_detailed!CC5/$AS$3 -> 0 | R5: =lc_detailed!CA5/$AS$3 -> 0 | S5: =lc_detailed!BE5 -> 1173.9374 | T5: =SUM(C5:Q5) -> 25.744241 | U5: =T5*$AS$3 -> 1173.9374 | W5: =lc_detailed!AZ5 -> SE_Ethanol_Dehydration_H2fuel | X5: =lc_detailed!BH5/$AS$3 -> 0.30171339 | Y5: =lc_detailed!BI5/$AS$3 -> 0.13417904 | Z5: =lc_detailed!BJ5/$AS$3 -> 0.15214612 | AA5: =lc_detailed!BK5/$AS$3 -> 0 | AB5: =lc_detailed!BL5/$AS$3 -> 14.800428 | AC5: =lc_detailed!BM5/$AS$3 -> 0 | AD5: =lc_detailed!BN5/$AS$3 -> 0.34050657 | AE5: =lc_detailed!BO5/$AS$3 -> 0.25972008 | ... AJ5: =lc_detailed!BT5/$AS$3 -> 7.6055102 | AK5: =lc_detailed!BV5/$AS$3 -> 0 | AL5: =lc_detailed!BW5/$AS$3 -> -8.4102014 | AM5: =lc_detailed!BU5/$AS$3 -> -0.068859649 | AN5: =lc_detailed!BB5 -> 790.4322 | AO5: =SUM(X5:AL5) -> 17.33404 | AP5: =AO5*$AS$3 -> 790.4322
B6: =lc_detailed!AZ6 -> CA_Ethanol_Dehydration_NGfuel | C6: =lc_detailed!BH6/$AS$3 -> 0 | D6: =lc_detailed!BI6/$AS$3 -> 0.12790046 | E6: =lc_detailed!BJ6/$AS$3 -> 0.14502681 | F6: =lc_detailed!BK6/$AS$3 -> 0 | G6: =lc_detailed!BL6/$AS$3 -> 14.800428 | H6: =lc_detailed!BM6/$AS$3 -> 0.41273547 | I6: =lc_detailed!BN6/$AS$3 -> 0.8288013 | J6: =lc_detailed!BO6/$AS$3 -> 0.25972008 | ... O6: =lc_detailed!BT6/$AS$3 -> 7.6055102 | P6: =lc_detailed!CB6/$AS$3 -> 0 | Q6: =lc_detailed!CC6/$AS$3 -> 0 | R6: =lc_detailed!CA6/$AS$3 -> 0 | S6: =lc_detailed!BE6 -> 1200.6553 | T6: =SUM(C6:Q6) -> 26.33016 | U6: =T6*$AS$3 -> 1200.6553 | W6: =lc_detailed!AZ6 -> CA_Ethanol_Dehydration_NGfuel | X6: =lc_detailed!BH6/$AS$3 -> 0 | Y6: =lc_detailed!BI6/$AS$3 -> 0.12790046 | Z6: =lc_detailed!BJ6/$AS$3 -> 0.14502681 | AA6: =lc_detailed!BK6/$AS$3 -> 0 | AB6: =lc_detailed!BL6/$AS$3 -> 14.800428 | AC6: =lc_detailed!BM6/$AS$3 -> 0.41273547 | AD6: =lc_detailed!BN6/$AS$3 -> 0.8288013 | AE6: =lc_detailed!BO6/$AS$3 -> 0.25972008 | ... AJ6: =lc_detailed!BT6/$AS$3 -> 7.6055102 | AK6: =lc_detailed!BV6/$AS$3 -> 0 | AL6: =lc_detailed!BW6/$AS$3 -> -8.4102014 | AM6: =lc_detailed!BU6/$AS$3 -> -0.068859649 | AN6: =lc_detailed!BB6 -> 817.15011 | AO6: =SUM(X6:AL6) -> 17.919958 | AP6: =AO6*$AS$3 -> 817.15011
B7: =lc_detailed!AZ7 -> CA_Ethanol_Dehydration_H2fuel | C7: =lc_detailed!BH7/$AS$3 -> 0.30804921 | D7: =lc_detailed!BI7/$AS$3 -> 0.12790046 | E7: =lc_detailed!BJ7/$AS$3 -> 0.14502681 | F7: =lc_detailed!BK7/$AS$3 -> 0 | G7: =lc_detailed!BL7/$AS$3 -> 14.800428 | H7: =lc_detailed!BM7/$AS$3 -> 0 | I7: =lc_detailed!BN7/$AS$3 -> 0.8288013 | J7: =lc_detailed!BO7/$AS$3 -> 0.25972008 | ... O7: =lc_detailed!BT7/$AS$3 -> 7.6055102 | P7: =lc_detailed!CB7/$AS$3 -> 0 | Q7: =lc_detailed!CC7/$AS$3 -> 0 | R7: =lc_detailed!CA7/$AS$3 -> 0 | S7: =lc_detailed!BE7 -> 1195.8816 | T7: =SUM(C7:Q7) -> 26.225474 | U7: =T7*$AS$3 -> 1195.8816 | W7: =lc_detailed!AZ7 -> CA_Ethanol_Dehydration_H2fuel | X7: =lc_detailed!BH7/$AS$3 -> 0.30804921 | Y7: =lc_detailed!BI7/$AS$3 -> 0.12790046 | Z7: =lc_detailed!BJ7/$AS$3 -> 0.14502681 | AA7: =lc_detailed!BK7/$AS$3 -> 0 | AB7: =lc_detailed!BL7/$AS$3 -> 14.800428 | AC7: =lc_detailed!BM7/$AS$3 -> 0 | AD7: =lc_detailed!BN7/$AS$3 -> 0.8288013 | AE7: =lc_detailed!BO7/$AS$3 -> 0.25972008 | ... AJ7: =lc_detailed!BT7/$AS$3 -> 7.6055102 | AK7: =lc_detailed!BV7/$AS$3 -> 0 | AL7: =lc_detailed!BW7/$AS$3 -> -8.4102014 | AM7: =lc_detailed!BU7/$AS$3 -> -0.068859649 | AN7: =lc_detailed!BB7 -> 812.37641 | AO7: =SUM(X7:AL7) -> 17.815272 | AP7: =AO7*$AS$3 -> 812.37641
B8: =lc_detailed!AZ8 -> SE_Ethanol_Dehydration_NGfuel_ethanol_biochemical | C8: =lc_detailed!BH8/$AS$3 -> 0 | D8: =lc_detailed!BI8/$AS$3 -> 0.13417904 | E8: =lc_detailed!BJ8/$AS$3 -> 0 | F8: =lc_detailed!BK8/$AS$3 -> -0.65401543 | G8: =lc_detailed!BL8/$AS$3 -> 11.981391 | H8: =lc_detailed!BM8/$AS$3 -> 0.16956916 | I8: =lc_detailed!BN8/$AS$3 -> 0 | J8: =lc_detailed!BO8/$AS$3 -> 0.25972008 | ... O8: =lc_detailed!BT8/$AS$3 -> 11.175722 | P8: =lc_detailed!CB8/$AS$3 -> 0 | Q8: =lc_detailed!CC8/$AS$3 -> 0 | R8: =lc_detailed!CA8/$AS$3 -> 0 | S8: =lc_detailed!BE8 -> 2053.3349 | T8: =SUM(C8:Q8) -> 45.029274 | U8: =T8*$AS$3 -> 2053.3349 | W8: =lc_detailed!AZ8 -> SE_Ethanol_Dehydration_NGfuel_ethanol_biochemical | X8: =lc_detailed!BH8/$AS$3 -> 0 | Y8: =lc_detailed!BI8/$AS$3 -> 0.13417904 | Z8: =lc_detailed!BJ8/$AS$3 -> 0 | AA8: =lc_detailed!BK8/$AS$3 -> -0.65401543 | AB8: =lc_detailed!BL8/$AS$3 -> 11.981391 | AC8: =lc_detailed!BM8/$AS$3 -> 0.16956916 | AD8: =lc_detailed!BN8/$AS$3 -> 0 | AE8: =lc_detailed!BO8/$AS$3 -> 0.25972008 | ... AJ8: =lc_detailed!BT8/$AS$3 -> 11.175722 | AK8: =lc_detailed!BV8/$AS$3 -> 0 | AL8: =lc_detailed!BW8/$AS$3 -> -8.4102014 | AM8: =lc_detailed!BU8/$AS$3 -> -0.068859649 | AN8: =lc_detailed!BB8 -> 1669.8297 | AO8: =SUM(X8:AL8) -> 36.619073 | AP8: =AO8*$AS$3 -> 1669.8297
B9: =lc_detailed!AZ9 -> SE_Ethanol_Dehydration_H2fuel_ethanol_biochemical | C9: =lc_detailed!BH9/$AS$3 -> 0.30171339 | D9: =lc_detailed!BI9/$AS$3 -> 0.13417904 | E9: =lc_detailed!BJ9/$AS$3 -> 0 | F9: =lc_detailed!BK9/$AS$3 -> -0.65401543 | G9: =lc_detailed!BL9/$AS$3 -> 11.981391 | H9: =lc_detailed!BM9/$AS$3 -> 0 | I9: =lc_detailed!BN9/$AS$3 -> 0 | J9: =lc_detailed!BO9/$AS$3 -> 0.25972008 | ... O9: =lc_detailed!BT9/$AS$3 -> 11.175722 | P9: =lc_detailed!CB9/$AS$3 -> 0 | Q9: =lc_detailed!CC9/$AS$3 -> 0 | R9: =lc_detailed!CA9/$AS$3 -> 0 | S9: =lc_detailed!BE9 -> 2059.3607 | T9: =SUM(C9:Q9) -> 45.161419 | U9: =T9*$AS$3 -> 2059.3607 | W9: =lc_detailed!AZ9 -> SE_Ethanol_Dehydration_H2fuel_ethanol_biochemical | X9: =lc_detailed!BH9/$AS$3 -> 0.30171339 | Y9: =lc_detailed!BI9/$AS$3 -> 0.13417904 | Z9: =lc_detailed!BJ9/$AS$3 -> 0 | AA9: =lc_detailed!BK9/$AS$3 -> -0.65401543 | AB9: =lc_detailed!BL9/$AS$3 -> 11.981391 | AC9: =lc_detailed!BM9/$AS$3 -> 0 | AD9: =lc_detailed!BN9/$AS$3 -> 0 | AE9: =lc_detailed!BO9/$AS$3 -> 0.25972008 | ... AJ9: =lc_detailed!BT9/$AS$3 -> 11.175722 | AK9: =lc_detailed!BV9/$AS$3 -> 0 | AL9: =lc_detailed!BW9/$AS$3 -> -8.4102014 | AM9: =lc_detailed!BU9/$AS$3 -> -0.068859649 | AN9: =lc_detailed!BB9 -> 1675.8555 | AO9: =SUM(X9:AL9) -> 36.751217 | AP9: =AO9*$AS$3 -> 1675.8555
B10: =lc_detailed!AZ10 -> CA_Ethanol_Dehydration_NGfuel_ethanol_biochemical | C10: =lc_detailed!BH10/$AS$3 -> 0 | D10: =lc_detailed!BI10/$AS$3 -> 0.12790046 | E10: =lc_detailed!BJ10/$AS$3 -> 0 | F10: =lc_detailed!BK10/$AS$3 -> -0.62341237 | G10: =lc_detailed!BL10/$AS$3 -> 14.614183 | H10: =lc_detailed!BM10/$AS$3 -> 0.41273547 | I10: =lc_detailed!BN10/$AS$3 -> 0 | J10: =lc_detailed!BO10/$AS$3 -> 0.25972008 | ... O10: =lc_detailed!BT10/$AS$3 -> 11.175722 | P10: =lc_detailed!CB10/$AS$3 -> 0 | Q10: =lc_detailed!CC10/$AS$3 -> 0 | R10: =lc_detailed!CA10/$AS$3 -> 0 | S10: =lc_detailed!BE10 -> 2185.5878 | T10: =SUM(C10:Q10) -> 47.929558 | U10: =T10*$AS$3 -> 2185.5878 | W10: =lc_detailed!AZ10 -> CA_Ethanol_Dehydration_NGfuel_ethanol_biochemical | X10: =lc_detailed!BH10/$AS$3 -> 0 | Y10: =lc_detailed!BI10/$AS$3 -> 0.12790046 | Z10: =lc_detailed!BJ10/$AS$3 -> 0 | AA10: =lc_detailed!BK10/$AS$3 -> -0.62341237 | AB10: =lc_detailed!BL10/$AS$3 -> 14.614183 | AC10: =lc_detailed!BM10/$AS$3 -> 0.41273547 | AD10: =lc_detailed!BN10/$AS$3 -> 0 | AE10: =lc_detailed!BO10/$AS$3 -> 0.25972008 | ... AJ10: =lc_detailed!BT10/$AS$3 -> 11.175722 | AK10: =lc_detailed!BV10/$AS$3 -> 0 | AL10: =lc_detailed!BW10/$AS$3 -> -8.4102014 | AM10: =lc_detailed!BU10/$AS$3 -> -0.068859649 | AN10: =lc_detailed!BB10 -> 1802.0826 | AO10: =SUM(X10:AL10) -> 39.519356 | AP10: =AO10*$AS$3 -> 1802.0826
B11: =lc_detailed!AZ11 -> CA_Ethanol_Dehydration_H2fuel_ethanol_biochemical | C11: =lc_detailed!BH11/$AS$3 -> 0.30804921 | D11: =lc_detailed!BI11/$AS$3 -> 0.12790046 | E11: =lc_detailed!BJ11/$AS$3 -> 0 | F11: =lc_detailed!BK11/$AS$3 -> -0.62341237 | G11: =lc_detailed!BL11/$AS$3 -> 14.614183 | H11: =lc_detailed!BM11/$AS$3 -> 0 | I11: =lc_detailed!BN11/$AS$3 -> 0 | J11: =lc_detailed!BO11/$AS$3 -> 0.25972008 | ... O11: =lc_detailed!BT11/$AS$3 -> 11.175722 | P11: =lc_detailed!CB11/$AS$3 -> 0 | Q11: =lc_detailed!CC11/$AS$3 -> 0 | R11: =lc_detailed!CA11/$AS$3 -> 0 | S11: =lc_detailed!BE11 -> 2180.8141 | T11: =SUM(C11:Q11) -> 47.824871 | U11: =T11*$AS$3 -> 2180.8141 | W11: =lc_detailed!AZ11 -> CA_Ethanol_Dehydration_H2fuel_ethanol_biochemical | X11: =lc_detailed!BH11/$AS$3 -> 0.30804921 | Y11: =lc_detailed!BI11/$AS$3 -> 0.12790046 | Z11: =lc_detailed!BJ11/$AS$3 -> 0 | AA11: =lc_detailed!BK11/$AS$3 -> -0.62341237 | AB11: =lc_detailed!BL11/$AS$3 -> 14.614183 | AC11: =lc_detailed!BM11/$AS$3 -> 0 | AD11: =lc_detailed!BN11/$AS$3 -> 0 | AE11: =lc_detailed!BO11/$AS$3 -> 0.25972008 | ... AJ11: =lc_detailed!BT11/$AS$3 -> 11.175722 | AK11: =lc_detailed!BV11/$AS$3 -> 0 | AL11: =lc_detailed!BW11/$AS$3 -> -8.4102014 | AM11: =lc_detailed!BU11/$AS$3 -> -0.068859649 | AN11: =lc_detailed!BB11 -> 1797.309 | AO11: =SUM(X11:AL11) -> 39.41467 | AP11: =AO11*$AS$3 -> 1797.309
B12: =lc_detailed!AZ12 -> 0 | C12: =lc_detailed!BH12/$AS$3 -> 0 | D12: =lc_detailed!BI12/$AS$3 -> 0 | E12: =lc_detailed!BJ12/$AS$3 -> 0 | F12: =lc_detailed!BK12/$AS$3 -> 0 | G12: =lc_detailed!BL12/$AS$3 -> 0 | H12: =lc_detailed!BM12/$AS$3 -> 0 | I12: =lc_detailed!BN12/$AS$3 -> 0 | J12: =lc_detailed!BO12/$AS$3 -> 0 | ... O12: =lc_detailed!BT12/$AS$3 -> 0 | P12: =lc_detailed!CB12/$AS$3 -> 0 | Q12: =lc_detailed!CC12/$AS$3 -> 0 | R12: =lc_detailed!CA12/$AS$3 -> 0 | S12: =lc_detailed!BE12 -> 0 | T12: =SUM(C12:Q12) -> 0 | U12: =T12*$AS$3 -> 0 | W12: =lc_detailed!AZ12 -> 0 | X12: =lc_detailed!BH12/$AS$3 -> 0 | Y12: =lc_detailed!BI12/$AS$3 -> 0 | Z12: =lc_detailed!BJ12/$AS$3 -> 0 | AA12: =lc_detailed!BK12/$AS$3 -> 0 | AB12: =lc_detailed!BL12/$AS$3 -> 0 | AC12: =lc_detailed!BM12/$AS$3 -> 0 | AD12: =lc_detailed!BN12/$AS$3 -> 0 | AE12: =lc_detailed!BO12/$AS$3 -> 0 | ... AJ12: =lc_detailed!BT12/$AS$3 -> 0 | AK12: =lc_detailed!BV12/$AS$3 -> 0 | AL12: =lc_detailed!BW12/$AS$3 -> 0 | AM12: =lc_detailed!BU12/$AS$3 -> 0 | AN12: =lc_detailed!BB12 -> 0 | AO12: =SUM(X12:AL12) -> 0 | AP12: =AO12*$AS$3 -> 0
B13: =lc_detailed!AZ13 -> 0 | C13: =lc_detailed!BH13/$AS$3 -> 0 | D13: =lc_detailed!BI13/$AS$3 -> 0 | E13: =lc_detailed!BJ13/$AS$3 -> 0 | F13: =lc_detailed!BK13/$AS$3 -> 0 | G13: =lc_detailed!BL13/$AS$3 -> 0 | H13: =lc_detailed!BM13/$AS$3 -> 0 | I13: =lc_detailed!BN13/$AS$3 -> 0 | J13: =lc_detailed!BO13/$AS$3 -> 0 | ... O13: =lc_detailed!BT13/$AS$3 -> 0 | P13: =lc_detailed!CB13/$AS$3 -> 0 | Q13: =lc_detailed!CC13/$AS$3 -> 0 | R13: =lc_detailed!CA13/$AS$3 -> 0 | S13: =lc_detailed!BE13 -> 0 | T13: =SUM(C13:Q13) -> 0 | U13: =T13*$AS$3 -> 0 | W13: =lc_detailed!AZ13 -> 0 | X13: =lc_detailed!BH13/$AS$3 -> 0 | Y13: =lc_detailed!BI13/$AS$3 -> 0 | Z13: =lc_detailed!BJ13/$AS$3 -> 0 | AA13: =lc_detailed!BK13/$AS$3 -> 0 | AB13: =lc_detailed!BL13/$AS$3 -> 0 | AC13: =lc_detailed!BM13/$AS$3 -> 0 | AD13: =lc_detailed!BN13/$AS$3 -> 0 | AE13: =lc_detailed!BO13/$AS$3 -> 0 | ... AJ13: =lc_detailed!BT13/$AS$3 -> 0 | AK13: =lc_detailed!BV13/$AS$3 -> 0 | AL13: =lc_detailed!BW13/$AS$3 -> 0 | AM13: =lc_detailed!BU13/$AS$3 -> 0 | AN13: =lc_detailed!BB13 -> 0 | AO13: =SUM(X13:AL13) -> 0 | AP13: =AO13*$AS$3 -> 0
B14: =lc_detailed!AZ14 -> 0 | C14: =lc_detailed!BH14/$AS$3 -> 0 | D14: =lc_detailed!BI14/$AS$3 -> 0 | E14: =lc_detailed!BJ14/$AS$3 -> 0 | F14: =lc_detailed!BK14/$AS$3 -> 0 | G14: =lc_detailed!BL14/$AS$3 -> 0 | H14: =lc_detailed!BM14/$AS$3 -> 0 | I14: =lc_detailed!BN14/$AS$3 -> 0 | J14: =lc_detailed!BO14/$AS$3 -> 0 | ... O14: =lc_detailed!BT14/$AS$3 -> 0 | P14: =lc_detailed!CB14/$AS$3 -> 0 | Q14: =lc_detailed!CC14/$AS$3 -> 0 | R14: =lc_detailed!CA14/$AS$3 -> 0 | S14: =lc_detailed!BE14 -> 0 | T14: =SUM(C14:Q14) -> 0 | U14: =T14*$AS$3 -> 0 | W14: =lc_detailed!AZ14 -> 0 | X14: =lc_detailed!BH14/$AS$3 -> 0 | Y14: =lc_detailed!BI14/$AS$3 -> 0 | Z14: =lc_detailed!BJ14/$AS$3 -> 0 | AA14: =lc_detailed!BK14/$AS$3 -> 0 | AB14: =lc_detailed!BL14/$AS$3 -> 0 | AC14: =lc_detailed!BM14/$AS$3 -> 0 | AD14: =lc_detailed!BN14/$AS$3 -> 0 | AE14: =lc_detailed!BO14/$AS$3 -> 0 | ... AJ14: =lc_detailed!BT14/$AS$3 -> 0 | AK14: =lc_detailed!BV14/$AS$3 -> 0 | AL14: =lc_detailed!BW14/$AS$3 -> 0 | AM14: =lc_detailed!BU14/$AS$3 -> 0 | AN14: =lc_detailed!BB14 -> 0 | AO14: =SUM(X14:AL14) -> 0 | AP14: =AO14*$AS$3 -> 0
B15: =lc_detailed!AZ15 -> 0 | C15: =lc_detailed!BH15/$AS$3 -> 0 | D15: =lc_detailed!BI15/$AS$3 -> 0 | E15: =lc_detailed!BJ15/$AS$3 -> 0 | F15: =lc_detailed!BK15/$AS$3 -> 0 | G15: =lc_detailed!BL15/$AS$3 -> 0 | H15: =lc_detailed!BM15/$AS$3 -> 0 | I15: =lc_detailed!BN15/$AS$3 -> 0 | J15: =lc_detailed!BO15/$AS$3 -> 0 | ... O15: =lc_detailed!BT15/$AS$3 -> 0 | P15: =lc_detailed!CB15/$AS$3 -> 0 | Q15: =lc_detailed!CC15/$AS$3 -> 0 | R15: =lc_detailed!CA15/$AS$3 -> 0 | S15: =lc_detailed!BE15 -> 0 | T15: =SUM(C15:Q15) -> 0 | U15: =T15*$AS$3 -> 0 | W15: =lc_detailed!AZ15 -> 0 | X15: =lc_detailed!BH15/$AS$3 -> 0 | Y15: =lc_detailed!BI15/$AS$3 -> 0 | Z15: =lc_detailed!BJ15/$AS$3 -> 0 | AA15: =lc_detailed!BK15/$AS$3 -> 0 | AB15: =lc_detailed!BL15/$AS$3 -> 0 | AC15: =lc_detailed!BM15/$AS$3 -> 0 | AD15: =lc_detailed!BN15/$AS$3 -> 0 | AE15: =lc_detailed!BO15/$AS$3 -> 0 | ... AJ15: =lc_detailed!BT15/$AS$3 -> 0 | AK15: =lc_detailed!BV15/$AS$3 -> 0 | AL15: =lc_detailed!BW15/$AS$3 -> 0 | AM15: =lc_detailed!BU15/$AS$3 -> 0 | AN15: =lc_detailed!BB15 -> 0 | AO15: =SUM(X15:AL15) -> 0 | AP15: =AO15*$AS$3 -> 0
... B59: =lc_detailed!AZ59 -> 0 | C59: =lc_detailed!BH59/$AS$3 -> 0 | D59: =lc_detailed!BI59/$AS$3 -> 0 | E59: =lc_detailed!BJ59/$AS$3 -> 0 | F59: =lc_detailed!BK59/$AS$3 -> 0 | G59: =lc_detailed!BL59/$AS$3 -> 0 | H59: =lc_detailed!BM59/$AS$3 -> 0 | I59: =lc_detailed!BN59/$AS$3 -> 0 | J59: =lc_detailed!BO59/$AS$3 -> 0 | ... O59: =lc_detailed!BT59/$AS$3 -> 0 | P59: =lc_detailed!CB59/$AS$3 -> 0 | Q59: =lc_detailed!CC59/$AS$3 -> 0 | R59: =lc_detailed!CA59/$AS$3 -> 0 | S59: =lc_detailed!BE59 -> 0 | T59: =SUM(C59:Q59) -> 0 | U59: =T59*$AS$3 -> 0 | W59: =lc_detailed!AZ59 -> 0 | X59: =lc_detailed!BH59/$AS$3 -> 0 | Y59: =lc_detailed!BI59/$AS$3 -> 0 | Z59: =lc_detailed!BJ59/$AS$3 -> 0 | AA59: =lc_detailed!BK59/$AS$3 -> 0 | AB59: =lc_detailed!BL59/$AS$3 -> 0 | AC59: =lc_detailed!BM59/$AS$3 -> 0 | AD59: =lc_detailed!BN59/$AS$3 -> 0 | AE59: =lc_detailed!BO59/$AS$3 -> 0 | ... AJ59: =lc_detailed!BT59/$AS$3 -> 0 | AK59: =lc_detailed!BV59/$AS$3 -> 0 | AL59: =lc_detailed!BW59/$AS$3 -> 0 | AM59: =lc_detailed!BU59/$AS$3 -> 0 | AN59: =lc_detailed!BB59 -> 0 | AO59: =SUM(X59:AL59) -> 0 | AP59: =AO59*$AS$3 -> 0
